Workbook

Sheet Overview
A1: DRAFT - Marine Cloud Brightening: Cost, Benefit, and Planetary-Scale Assessment
A3: Intent
A4: The intent of this workbook is to do bottom up assessment of marine cloud brightening. The intent is to use the best available academic sources and connect those pieces together for this end to end assessment. Then we work through different delivery mechanisms, whether a dedicated vessel, piggybacking on a cargo ship, fixed platforms, or stationary vessels.
A5: Methodology
A6: Wherever possible, our intent is to use academic sources for inputs. On the last tab, references, you can find all the papers that we pulled data from. In this sense, we're pulling parts of a shelf and attempting to assemble them. As the foundation we take the exact numbers from Daniel Harrison's prototype in the Great Barrier Reef. However, these "parts" weren't built to be put together. This has two effects. One is that we may be connecting them together in the wrong order. The second is there are gaps, which means we make assumptions, which are not academically sourced.
A7: How the Workbook is Organized
A8: The workbook is broken roughly into two parts. The first section is modeling a machine/ship that spits out aerosol particles. The second section is then figuring out what the climate effect and outcome of those particles is.
A9: Particle cost model (tabs 1-4): what it costs to produce and spray particles
A10: 1. Technology Description: the spray machine. CCN product = 30-1000 nm particles (Harrison 2025 convention).
A11: 2. Cost Inputs: the blue input cells (capital, energy, crew, unit costs).
A12: 3a. Outputs - Dedicated Vessel: levelized cost per tonne of aerosol (the anchor number).
A13: 3b/3c/3d: cheaper siting and delivery vs a dedicated vessel (piggyback, fixed platform, stationary).
... A31: Tito Jankowski, tito.jankowski@renphil.org

Sheet 1. Technology Description
A1: DRAFT - Technology Description
A3: System Definition
A4: A single effervescent nozzle: seawater + compressed air + power in, CCN aerosol out. TEA stops at particle production; climatology on subsequent tabs
A6: Particle Production
A7: Quantity | B7: Value | C7: Unit | D7: Notes / Source | E7: Sources
A8: Particle output | B8: 1730000000000 | C8: particles/s | D8: Harrison et al. 2025, Environ. Sci.: Atmos. 5, 1071-1080 (doi:10.1039/d5ea00073d, OA; RSC blocks automated download, get PDF via DOI): ~1.73e12 droplets/s per nozzle. Cross-checks from files held: CS-06 Final Report 2025, p.24: the 2020 sea trial made "an estimated 2.7 x 10^14 droplets per second" from a "100 nozzle fan driven array [that] matched that of a single nozzle characterised under laboratory conditions" (about 2.7e12 per nozzle); CS-06 p.1: current prototype "~10^15 s-1 sea salt aerosols using 320 kilowatts (kW) of energy" (about 1.6e12 per nozzle over 640 nozzles). | E8: Harrison et al. 2025, Environ. Sci.: Atmos. 5, 1071-1080 (doi:10.1039/d5ea00073d).
A9: CCN-production window fraction (30-1000 nm) | B9: 0.71 | D9: Harrison 2025 (doi:10.1039/d5ea00073d): CCN production rate = counts in the 30-1000 nm window (~71%). No separate activation cut (would double-count). Field target window is tighter, CS-06 Final Report 2025, p.12, Fig. 5 caption: "Green shading indicates a MCB target range of 30-800 nm dry diameter." | E9: Harrison et al. 2025, Environ. Sci.: Atmos. 5, 1071-1080 (doi:10.1039/d5ea00073d).
A10: Dry particle diameter | B10: 150 | C10: nm | D10: One important note this model currently does not respond to changes in particle size. It calls all particles equivalent as long as they're within a certain range. Design value stays mass-weighted; mass sits in the large tail. Count mode is much smaller: CS-06 Final Report 2025, p.24: "mode dry aerosol diameter around 40 nm"; ERL 2025 (doi:10.1088/1748-9326/adccd7), p.6: sea-salt plume has "a notable peak at 47.03 nm average". Count-equivalent from the measured count + mass: ~143 nm. | E10: CS-06 Final Report 2025, p.24 + ERL 2025 p.6 (doi:10.1088/1748-9326/adccd7).
A11: Particles per tonne of salt | B11: =1000/B12 -> 2.6198345e+20 | C11: particles/tonne | D11: Field count runs ~15% higher than the lab math (2020 GBR trial; Hernandez-Jaramillo 2025), so cooling cost may come out slightly high. Tab 5a pulls this cell.
A12: Mass per dry particle | B12: =PI()/6*(B10*10^-9)^3*2160 -> 3.8170351e-18 | C12: kg | D12: Sphere volume x dry NaCl density 2160 kg/m3.
A13: CCN-production output (30-1000 nm window) | B13: =B8*B9*B12*86400*1000 -> 405.08331 | C13: g/day | D13: per nozzle particle rate x window fraction x dry mass x time. Window output is the product (Harrison 2025); plume survival charged per-scenario on 5a/6a.
A14: CCN-production output (30-1000 nm window) | B14: =B13/1000000 -> 0.00040508331 | C14: tonne/day
A16: Energy | G16: Nozzle power scenario (selector)
A17: Power | B17: =CHOOSE($H$17,$H$18,$H$19) -> 512 | C17: W | D17: Set by the scenario selector in H17 (1 = measured 512 W, 2 = CS-06 10x energy target 51.2 W). Harrison 2025 (doi:10.1039/d5ea00073d): nozzle power, ~98% air compression. Scale check from file held, CS-06 Final Report 2025, p.1: "The current prototype produces ~10^15 s-1 sea salt aerosols using 320 kilowatts (kW) of energy", about 0.32 W per 1e9 particles/s, i.e. ~550 W per nozzle at 1.73e12/s. Consistent with 512 W. | E17: Harrison et al. 2025, Environ. Sci.: Atmos. 5, 1071-1080 (doi:10.1039/d5ea00073d); scale check vs CS-06 Final Report 2025, p.1 | G17: Selected scenario | H17: 1 | I17: enter 1 or 2
A18: Energy per hour | B18: =B17/1000 -> 0.512 | C18: kWh | G18: 1: Harrison 2025 as measured | H18: 512 | I18: W
A19: Energy per day | B19: =B18*24 -> 12.288 | C19: kWh | G19: 2: CS-06 10x energy target | H19: 51.2 | I19: W
A20: Efficiency: energy per tonne of aerosol | B20: =B19/B14 -> 30334.501 | C20: kWh/tonne | D20: x power price = marginal $/tonne (~$9,100 at $0.30/kWh diesel). CS-06's ARIEL is roughly equal per-particle; CS-06 wants a further ~10x. | G20: B17 reads the selection; tab 2 and every output tab read B17.
A22: Water Handling
A23: Seawater flow rate | B23: 0.41 | C23: mL/s | D23: Harrison 2025 (doi:10.1039/d5ea00073d): ~1.73e12 droplets/s from 0.41 mL/s filtered seawater + 0.3 L/s air per nozzle. Field rigs run lower per nozzle: ERL 2025 (doi:10.1088/1748-9326/adccd7), p.2: "320 effervescent nozzles ... assembled into 5 manifold towers atomising a total of 68 ml s-1 of seawater" (about 0.21 mL/s each). Per-second value; next row converts to daily. | E23: Harrison et al. 2025, Environ. Sci.: Atmos. 5, 1071-1080 (doi:10.1039/d5ea00073d); field config: ERL 2025, p.2.
A24: Seawater sprayed | B24: =B23*86.4 -> 35.424 | C24: L/day | D24: 0.41 mL/s x 86,400 = per-day volume, converted once here so downstream stays in day-units. Only ~3.5% is salt.
A25: Seawater intensity | B25: =B24/(B13/1000000)/1000 -> 87.448679 | C25: m3/tonne | D25: Wet volume handled per dry tonne of CCN. Drives pumping/filtration/UV energy (x 0.6 kWh/m3 on Cost Inputs). Computed from the output of Harrison's 2025 nozzle.
A26: Pumping + filtration + UV energy | B26: 0.6 | C26: kWh per m3 seawater | D26: Electricity to lift, filter and UV-treat one cubic metre of seawater before atomizing. Assumption; until 10/07 this 0.6 was typed inside formulas on tab 2 (B28) and tab 3a (row 37, column AI).
A27: Process Flow
B29: Seawater intake
B30: ↓
B31: Filtration + UV
B32: ↓
B33: Pressurize seawater
B34: ↓
B35: Compress air
B36: ↓
B37: Effervescent nozzle
B38: ↓
B39: Evaporation
B40: ↓
... B52: Cooling Conversion

Sheet 2. Cost Inputs
A1: DRAFT - Cost Input Sheet
A2: General Parameters
B4: Value | C4: Unit | E4: Notes / Source | F4: Sources
A5: Equipment availability | B5: 0.9 | C5: fraction | E5: Mechanical uptime of the system, accounting for repairs and maintenance downtime | F5: Assumption (mechanical uptime target).
A6: Project lifetime | B6: 15 | C6: years | E6: Hardware life | F6: Assumption (hardware life).
A7: Discount rate | B7: 0.1 | E7: Cost of capital | F7: Assumption (cost of capital).
A8: Exchange rate, AUD to USD | B8: 0.7 | C8: USD per AUD | E8: Used by tab 5c to convert the A$ reef valuation. Until 10/07 typed inside 5c B27. | F8: Assumption (0.70 USD/AUD).
A9: Equipment Sizing
B10: Value | C10: Unit | E10: Notes / Source | F10: Sources
A11: Aerosol per nozzle per year | B11: ='1. Technology Description'!B13*365*$B$5/1000000 -> 0.13306987 | C11: tonnes/yr | E11: g/day x 365 x equipment availability, to tonnes
A12: Particle flux per vessel-unit | B12: =B13*'1. Technology Description'!B8*'1. Technology Description'!B9 -> 1e+16 | C12: particles/s | E12: Output now: nozzles x rate x window fraction. Shows 10^16/s at base (Latham et al. 2012, ~10^15-10^16/s per sprayer); it is no longer a requirement.
A13: Nozzle count (per vessel-unit) | B13: =B14*1000/'1. Technology Description'!B17 -> 8141.3336 | C13: nozzles | E13: Spray power (B14) / watts per nozzle (tab 1 B17). Until 10/07 this was 10^16/s / particles per nozzle, so a better nozzle meant the same count at lower power instead of more nozzles on the same plant.
A14: Spray power per vessel-unit | B14: 4168.3628 | C14: kW | E14: The sizing lever since 10/07: the vessel is built around this power plant and carries as many nozzles as it can run (B13). 4,168 kW = 8,142 nozzles at Harrison's 512 W, so the base case is unchanged. At 51 W the same plant runs 81,400 nozzles: no one has checked that many booms and manifolds (127 ARIEL rigs) fit the modelled vessel, and the seawater intake would be 33 L/s. Same approach as the piggyback's 4.5 MW on tab 3b. | F14: Model structure (power-sized vessel-unit, 10/07). Harrison 2025: 814 nozzles at 10^15/s need 417 kW; 10^16/s about 4.2 MW.
A15: Annual production per vessel-unit (equipment basis) | B15: =B13*B11 -> 1083.3662 | C15: tonnes/yr | E15: Nozzle count x aerosol per nozzle-year (equipment basis)
A17: Operating Expenditure (annual)
A18: 1. Raw Materials
B19: Amount | C19: Unit | D19: Cost/Unit | E19: Notes / Source | F19: Sources
A20: Seawater | B20: ='1. Technology Description'!B25*1000 -> 87448.679 | C20: L/tonne | D20: 0 | E20: Drawn from the sea | F20: Structural: seawater drawn at sea, no purchase cost.
A22: 2. Process Energy
B23: Amount | C23: Unit | D23: Cost/Unit
A24: Energy (compression, atomizes wet seawater) | B24: ='1. Technology Description'!B20 -> 30334.501 | C24: kWh/tonne | D24: 0.3 | E24: Power x 24h per nozzle / aerosol per nozzle. | F24: Derived: tab-1 nozzle power (Harrison 2025) x 24 h x energy price assumption.
A25: Vessel propulsion burn (underway) | B25: 16000 | C25: L/day | D25: 0.9 | E25: PSV cruise ~16.4 m3/day at 10 kn, 22.7 at 12 kn (UT 755L); Adland PSV average ~9.3 t/day. | F25: Vessel spec sheets (websites, not downloaded): UT 755L PSV ~16.4 m3/day at 10 kn; Adland PSV average ~9.3 t/day. Links: https://horizonoffshoreservices.com/wp-content/uploads/2024/07/HOS269.pdf ; https://www.mdpi.com/2077-1312/13/4/686
A26: Vessel hotel burn (at rest / on station) | B26: 2700 | C26: L/day | D26: =D25 -> 0.9 | E26: Hotel plus light station-keeping.
A27: Fuel tank capacity | B27: 1000000 | C27: L
A28: Seawater pumping + filtration + UV | B28: ='1. Technology Description'!B25*'1. Technology Description'!B26 -> 52.469208 | C28: kWh/tonne | D28: 0.3 | E28: Lift, filter, UV-treat seawater before atomizing. Scales with wet volume (~87 m3 per dry tonne). | F28: Assumption: scales with wet volume (~87 m3 per dry tonne).
A29: 3. Labor
B30: Amount | C30: Unit | D30: Cost/Unit
A31: Crew | B31: 6 | C31: crew | D31: 150000 | E31: 6 crew per vessel x vessels (base scenario vessel count lives on tab 3a). | F31: Assumption: 6 crew per vessel.
A33: 4. Fixed Operating Expenditure
B34: Amount | C34: Unit
A35: Maintenance & insurance | B35: 0.07 | C35: of capex/yr | E35: 5% maintenance + 2% insurance | F35: Assumption: 5% maintenance + 2% insurance of capital.
A37: Capital Expenditure
A38: 5. Purchased Equipment
B39: Amount | C39: Unit | D39: Cost/Unit | E39: Notes / Source | F39: Sources | G39: Nozzle unit cost scenario (selector)
A40: Nozzles & manifolds | B40: =B13 -> 8141.3336 | C40: nozzles | D40: =CHOOSE($H$40,$H$41,$H$42,$H$43) -> 100 | E40: No published price for the SCU/ARIEL effervescent nozzle (searched Harrison 2025, CS-01/04/06/07, T14, ARIA proposal, Hernandez-Jaramillo thesis, 10/07). Bracket: CS-07 2025 p.31 'commercially proven nozzles ... ~$10 to ~$1000 each', marine 316 SS 'considerably more expensive'; CS-07 p.35 MeeFog manifolds 'about US$50 per nozzle, including nozzles, adapters, fittings, support frame'; CS-06 p.23 cartridge redesign 'significantly reducing costs'. Scenario 2 ($100) assumes the prototype nozzle unchanged, just made in volume. Compressors are priced separately (row 41). Installation (row 51) is 20% of equipment, so it scales with this price; a flat per-nozzle labour cost would be more honest at $10. | F40: RRAP CS-07 Fogging Development Final Report 2025, p.31 and p.35 (MeeFog manifold US$50/nozzle); RRAP CS-06 Final Report 2025, p.23 (cartridge nozzle). No price for the ARIEL nozzle in any Harrison-group publication. | G40: Selected scenario | H40: 2 | I40: enter 1, 2 or 3
A41: Compression + generation | B41: =B14 -> 4168.3628 | C41: kW | D41: 1500 | E41: Used Ariel 200 hp CNG compressor package listed $180k ≈ $1,200/kW (Bakersfield yard listing). Link: https://inventory.freeoilfieldquote.com/product/ariel-jgq-2-3-200-hp-vfd-electric-drive-3-stage-cng-com | F41: Market reference (website): used Ariel 200 hp CNG compressor package listed $180k, ~$1,200/kW (Bakersfield yard listing). Link: https://inventory.freeoilfieldquote.com/product/ariel-jgq-2-3-200-hp-vfd-electric-drive-3-stage-cng-com | G41: 1: $10, commodity nozzle at volume | H41: 10 | I41: $/nozzle
A42: Seawater intake/filtration/UV | B42: 1 | C42: per vessel | D42: 25000 | E42: $25k marinized: pump + strainer + polish + UV + spares. Ballast-water systems cost $640k+ but treat ~1,000x our throughput (Transport Canada, Transactions on BWTS 2015). | F42: Assumption ($25k marinized); ballast-water treatment systems ($640k+, Transport Canada 'Transactions on BWTS' 2015) as comparator at ~1,000x throughput. Link: https://www.tc.canada.ca/sites/default/files/migrated/transactions_for_bwts_on_the_great_lakes___transport_canada.pdf | G42: 2: $100, cartridge nozzle in a welded manifold, made in volume | H42: 100 | I42: $/nozzle
A43: Vessel structure & integration | B43: 1 | C43: per vessel | D43: =D44*0.25 -> 7500000 | E43: Assumption: nothing published exists for installing a ~1,000-nozzle spray array. Set at 25% of vessel cost. | G43: 3: $1,000, installed research-grade nozzle | H43: 1000 | I43: $/nozzle
A44: Vessel purchase | B44: 1 | C44: vessels | D44: 30000000 | E44: Newbuild 70-80 m PSV (Clarksons basis), sized for the ~3 MW spray plant. Platform = ~6-7 such vessels (sizing block below). | F44: Market reference (website): newbuild 70-80 m PSV, Clarksons basis; sized for the ~3 MW spray plant. Link: https://www.rivieramm.com/news-content-hub/sticker-shock-price-of-psv-newbuildings-up-68-since-2016-79964 | G44: D40 reads the selection; every capex line reads D40. The 3a tornado runs $10 to $1,000 regardless of the selection.
A45: Total purchased equipment | B45: =B40*D40+B41*D41+B42*D42+B43*D43+B44*D44 -> 44591678
A47: 6. Contingency & Indirect Capital | E47: Notes / Source | F47: Sources
B48: Fraction
A49: Engineering & supervision | B49: 0.2 | F49: Assumption (share of capital).
A50: Installation & commissioning | B50: 0.15 | F50: Assumption (share of capital).
A51: Marinization premium | B51: 0.2 | C51: =((D42*B42)+(D40*B40)+(D41*B41))*B51 -> 1418335.5 | E51: Corrosion, classification, maintenance access; applied to equipment, not the vessel. | F51: Assumption (marinization premium on equipment).
A52: Process contingency | B52: 0.25 | F52: Assumption (process contingency).
A53: Total capex | B53: =B45*(1+B49+B50+B52)+C51 -> 72765020
A55: 7. Charter Rate | E55: Notes / Source
A56: Bareboat charter rate, workboat class (hull + crew) | B56: 150000 | C56: $/vessel/week | D56: Assumption, no market quote (moved from tab 5d). Hull and crew only; the spray gear is charged separately in B58. Until 10/07 this cell was total capex / 2000 per day, a kitted-vessel rate. | E56: This is a rough estimate. Total capex divided by 2000. Wanted some way to be able to break the cost down for charter scenarios like the Reef scenario. Indendent to represent the hull, crew, and insurance.
A57: Spray-train capex per vessel-unit (mounted gear, excl. hull) | B57: =(B40*D40+B41*D41+B42*D42)*(1+B49+B50+B52)+C51 -> 12765020 | C57: $ | D57: Nozzles + compressors/gensets + seawater skid, with the contingency stack and installation. What gets mounted on a chartered hull (5c, 5c-alt, 5d).
A58: Spray-train capital charge per vessel-day | B58: =B57*((B7*(1+B7)^B6)/((1+B7)^B6-1))/365 -> 4597.9872 | C58: $/vessel/day | D58: B57 x capital recovery factor (B6, B7) / 365. Charged per vessel-day of a chartered campaign.

Sheet 3a. Outputs - Dedicated Vessel
A1: Output Sheet
A3: Annualized Cost Build-up | F3: Key Metrics
A4: Component | B4: Annual cost | C4: $/tonne of aerosol | D4: % of total | F4: Metric | G4: Value | H4: Unit
A5: Capital recovery factor | B5: =('2. Cost Inputs'!B7*(1+'2. Cost Inputs'!B7)^'2. Cost Inputs'!B6)/((1+'2. Cost Inputs'!B7)^'2. Cost Inputs'!B6-1) -> 0.13147378 | F5: Levelized cost of aerosol | G5: =B13/$B$22 -> 54047.979 | H5: $/tonne of aerosol
A6: Annualized capital | B6: ='2. Cost Inputs'!B53*B5 -> 9566691.9 | C6: =B6/$B$22 -> 24173.562 | D6: =B6/$B$13 -> 0.44726117 | F6: Annual aerosol production | G6: =$B$22 -> 395.7502 | H6: tonnes/yr
A7: Energy | B7: ='2. Cost Inputs'!B24*'2. Cost Inputs'!D24*$B$22 -> 3601465.4 | C7: =B7/$B$22 -> 9100.3504 | D7: =B7/$B$13 -> 0.16837541 | F7: Total capex | G7: ='2. Cost Inputs'!B53 -> 72765020 | H7: $
A8: Seawater pumping + filtration | B8: ='2. Cost Inputs'!B28*'2. Cost Inputs'!D28*$B$22 -> 6229.4098 | C8: =B8/$B$22 -> 15.740762 | D8: =B8/$B$13 -> 0.00029123684 | F8: Total annual cost | G8: =B13 -> 21389498 | H8: $/yr
A9: Seawater feedstock | B9: ='2. Cost Inputs'!B20*'2. Cost Inputs'!D20*$B$22 -> 0 | C9: =B9/$B$22 -> 0 | D9: =B9/$B$13 -> 0 | F9: Nozzles per system | G9: ='2. Cost Inputs'!B13 -> 8141.3336 | H9: nozzles
A10: Crew | B10: ='2. Cost Inputs'!B31*'2. Cost Inputs'!D31 -> 900000 | C10: =B10/$B$22 -> 2274.1619 | D10: =B10/$B$13 -> 0.042076724 | F10: Operating days per year | G10: =B21 -> 132 | H10: days/yr
A11: Maintenance & insurance | B11: ='2. Cost Inputs'!B53*'2. Cost Inputs'!B35 -> 5093551.4 | C11: =B11/$B$22 -> 12870.622 | D11: =B11/$B$13 -> 0.23813328 | F11: Spray power | G11: ='2. Cost Inputs'!B14 -> 4168.3628 | H11: kW
A12: Vessel energy | B12: =(B24+B25)*'2. Cost Inputs'!D25 -> 2221560 | C12: =B12/$B$22 -> 5613.5411 | D12: =B12/$B$13 -> 0.10386218 | F12: Capex share of annual cost | G12: =B6/B13 -> 0.44726117 | H12: fraction
A13: Total Annual Cost | B13: =SUM(B6:B12) -> 21389498 | C13: =B13/$B$22 -> 54047.979 | D13: =1 -> 1 | F13: Variable cost share | G13: =(B7+B8)/B13 -> 0.16866664 | H13: fraction
F14: Cost per delivered tonne | G14: =G5/'5a. Cooling Model - Local'!B5 -> 180159.93 | H14: $/tonne delivered at cloud base
A16: Mission & Endurance
A17: Component | E17: Notes | I17: Sources
A18: Spray time - moving (underway) | B18: 0.3652968 | C18: % of avail. time | E18: Spraying while the vessel is underway - the dedicated vessel sprays on the move | I18: Assumption: dedicated vessel sprays underway.
A19: Spray time - on station | B19: 0 | C19: % of avail. time | E19: Spraying while holding station; zero for the dedicated vessel | I19: Assumption: zero on-station for this scenario.
A20: Transit time (no spray) | B20: 0.03652968 | C20: % of avail. time | E20: Repositioning between spray areas plus refuel legs; only propulsion+hotel burn | I20: Assumption: repositioning + refuel legs.
A21: Operating days per year | B21: =(B18+B19+B20)*365*'2. Cost Inputs'!$B$5 -> 132 | C21: days | E21: = (spray + transit) % of available time x 365 x equipment availability
A22: Effective production | B22: =(B18+B19)*'2. Cost Inputs'!$B$15 -> 395.7502 | C22: tonnes/yr | E22: = spray % x equipment-basis annual production (availability already applied)
A23: Endurance per tank | B23: =$B$26*'2. Cost Inputs'!B27/('2. Cost Inputs'!B25+'2. Cost Inputs'!B26) -> 48.128342 | C23: days | E23: 90% of tank at combined underway burn (propulsion + hotel)
A24: Vessel fuel per year (propulsion) | B24: =(B18+B20)*365*'2. Cost Inputs'!$B$5*'2. Cost Inputs'!B25 -> 2112000 | C24: L/yr | E24: = (spray-moving + transit) % x 365 x availability x underway burn
A25: Hotel fuel per year | B25: =B21*'2. Cost Inputs'!B26 -> 356400 | C25: L/yr | E25: = operating days x hotel burn
A26: Usable fraction of fuel tank | B26: 0.9 | C26: fraction | E26: Tanks are not run dry; 90% usable. Read by B23 here and by tab 3d. Until 10/07 typed inside both formulas.
A27: Levelized cost per tonne of aerosol
A28: Cost build-up with every tornado input at worst / base / best. Particle size fixed; only power per unit varies for nozzle improvements.
A30: Component | B30: Pessimistic | C30: Base | D30: Optimistic
A31: Production (t/yr) | B31: ='2. Cost Inputs'!B15*(B53/'2. Cost Inputs'!$B$5) -> 237.45012 | C31: ='2. Cost Inputs'!B15*(C53/'2. Cost Inputs'!$B$5) -> 395.7502 | D31: ='2. Cost Inputs'!B15*(D53/'2. Cost Inputs'!$B$5) -> 514.47526
A32: Energy intensity (kWh/tonne) | B32: =B49*24/1000/('1. Technology Description'!B13/10^6) -> 45501.752 | C32: =C49*24/1000/('1. Technology Description'!B13/10^6) -> 30334.501 | D32: =D49*24/1000/('1. Technology Description'!B13/10^6) -> 3033.4501
A33: Total capex ($) | B33: =('2. Cost Inputs'!B13*B54+'2. Cost Inputs'!B13*B49/1000*B59+1*('2. Cost Inputs'!D42+'2. Cost Inputs'!D43+'2. Cost Inputs'!D44))*(1+'2. Cost Inputs'!B49+'2. Cost Inputs'!B50+'2. Cost Inputs'!B51+'2. Cost Inputs'!B52) -> 1.075222e+08 | C33: =('2. Cost Inputs'!B13*C54+'2. Cost Inputs'!B13*C49/1000*C59+1*('2. Cost Inputs'!D42+'2. Cost Inputs'!D43+'2. Cost Inputs'!D44))*(1+'2. Cost Inputs'!B49+'2. Cost Inputs'!B50+'2. Cost Inputs'!B51+'2. Cost Inputs'!B52) -> 80265020 | D33: =('2. Cost Inputs'!B13*D54+'2. Cost Inputs'!B13*D49/1000*D59+1*('2. Cost Inputs'!D42+'2. Cost Inputs'!D43+'2. Cost Inputs'!D44))*(1+'2. Cost Inputs'!B49+'2. Cost Inputs'!B50+'2. Cost Inputs'!B51+'2. Cost Inputs'!B52) -> 68366819
A34: Capital recovery factor | B34: =(B57*(1+B57)^'2. Cost Inputs'!B6)/((1+B57)^'2. Cost Inputs'!B6-1) -> 0.17101705 | C34: =(C57*(1+C57)^'2. Cost Inputs'!B6)/((1+C57)^'2. Cost Inputs'!B6-1) -> 0.13147378 | D34: =(D57*(1+D57)^'2. Cost Inputs'!B6)/((1+D57)^'2. Cost Inputs'!B6-1) -> 0.10296276
A35: Annualized capital ($/yr) | B35: =B33*B34 -> 18388130 | C35: =C33*C34 -> 10552745 | D35: =D33*D34 -> 7039236.6
A36: Spray energy ($/yr) | B36: =B32*B58*B31 -> 4861978.3 | C36: =C32*C58*C31 -> 3601465.4 | D36: =D32*D58*D31 -> 280914.3
A37: Seawater pumping + UV ($/yr) | B37: ='2. Cost Inputs'!$B$28*'2. Cost Inputs'!$D$28*B31 -> 3737.6459 | C37: ='2. Cost Inputs'!$B$28*'2. Cost Inputs'!$D$28*C31 -> 6229.4098 | D37: ='2. Cost Inputs'!$B$28*'2. Cost Inputs'!$D$28*D31 -> 8098.2327 | E37: kWh/tonne (tab 2 B28) x price x production for the case. Until 10/07 this row used litres where it needed cubic metres, 1,000x low on a ~$16/tonne line.
A38: Crew ($/yr) | B38: =1*6*B52 -> 1260000 | C38: =1*6*C52 -> 900000 | D38: =1*6*D52 -> 630000
A39: Maintenance & insurance ($/yr) | B39: =B33*B56 -> 12042487 | C39: =C33*C56 -> 5618551.4 | D39: =D33*D56 -> 2392838.7
A40: Vessel energy ($/yr) | B40: =B51*'2. Cost Inputs'!D25*1 -> 2851200 | C40: =C51*'2. Cost Inputs'!D25*1 -> 1900800 | D40: =D51*'2. Cost Inputs'!D25*1 -> 950400
A41: Levelized cost ($/tonne) | B41: =SUM(B35:B40)/B31 -> 165961.31 | C41: =SUM(C35:C40)/C31 -> 57055.667 | D41: =SUM(D35:D40)/D31 -> 21967.019
A45: Sensitivity Analysis
A47: Tornado Diagram Inputs
A48: Variable | B48: Pessimistic | C48: Base Case | D48: Optimistic | E48: Units | F48: Description | I48: Live calc, drives the tornado (safe to hide columns R:AS)
A49: Power per unit | B49: =C49*1.5 -> 768 | C49: ='1. Technology Description'!B17 -> 512 | D49: =C49*0.1 -> 51.2 | E49: W | F49: Worst = 1.5x (degradation/losses). Best = 0.1x miracle machine (electrospray-class): same rate at one-tenth power. | J49: d | K49: util | L49: disc | M49: nozcost | N49: compcost | O49: vescost | P49: maint | Q49: eprice | R49: vfuel | S49: crew | AJ49: $/tonne of aerosol
A50: Particle output rate | B50: =C50*0.85 -> 1470500000000 | C50: ='1. Technology Description'!B8 -> 1730000000000 | D50: =C50*1.15 -> 1.9895e+12 | E50: particles/s | F50: Harrison et al. 2025: field count rate runs ~15% above the lab value (2020 GBR trial vs CS-06 bench); +/-15% band. | J50: ='1. Technology Description'!$B$10 -> 150 | K50: =($B$18+$B$19)*'2. Cost Inputs'!$B$5 -> 0.32876712 | L50: ='2. Cost Inputs'!$B$7 -> 0.1 | M50: ='2. Cost Inputs'!$D$40 -> 100 | N50: ='2. Cost Inputs'!$D$41 -> 1500 | O50: ='2. Cost Inputs'!$D$43 -> 7500000 | P50: ='2. Cost Inputs'!$B$35 -> 0.07 | Q50: ='2. Cost Inputs'!$D$24 -> 0.3 | R50: =('2. Cost Inputs'!$B$25*($B$18+$B$20)*365*'2. Cost Inputs'!$B$5) -> 2112000 | S50: ='2. Cost Inputs'!$D$31 -> 150000 | T50: =PI()/6*(J50*10^-9)^3*2160 -> 3.8170351e-18 | U50: ='1. Technology Description'!$B$8*'1. Technology Description'!$B$9*T50*86400*1000 -> 405.08331 | V50: =U50*365*K50/1000000 -> 0.048609997 | W50: =ROUNDUP($B$22/V50,0) -> 8142 | X50: =W50*'1. Technology Description'!$B$17/1000 -> 4168.704 | Y50: =1 -> 1 | Z50: =W50*M50+X50*N50+Y50*'2. Cost Inputs'!$D$42+Y50*O50+Y50*'2. Cost Inputs'!$D$44 -> 44592256 | AA50: =Z50*(1+'2. Cost Inputs'!$B$49+'2. Cost Inputs'!$B$50+'2. Cost Inputs'!$B$52)+(W50*M50+X50*N50+Y50*'2. Cost Inputs'!$D$42)*'2. Cost Inputs'!$B$51 -> 72766061 | AB50: =(L50*(1+L50)^'2. Cost Inputs'!$B$6)/((1+L50)^'2. Cost Inputs'!$B$6-1) -> 0.13147378 | AC50: =AA50*AB50 -> 9566828.8 | AD50: ='1. Technology Description'!$B$17*24/1000/(U50/1000000) -> 30334.501 | AE50: =AD50*Q50*$B$22 -> 3601465.4 | AF50: =Y50*6*S50 -> 900000 | AG50: =AA50*P50 -> 5093624.3 | AH50: =R50*'2. Cost Inputs'!$D$25*Y50 -> 1900800 | AI50: =AC50+AE50+AF50+AG50+AH50+(('1. Technology Description'!$B$24/(U50/1000000)/1000)*'1. Technology Description'!$B$26*'2. Cost Inputs'!$D$28*$B$22) -> 21068948 | AJ50: =AI50/$B$22 -> 53237.997
A51: Vessel fuel/yr | B51: =C51*1.5 -> 3168000 | C51: =('2. Cost Inputs'!$B$25*($B$18+$B$20)*365*'2. Cost Inputs'!$B$5) -> 2112000 | D51: =C51*0.5 -> 1056000 | E51: L/vessel/yr | F51: Propulsion + hotel, dedicated vessel | J51: =$B$49 -> 768 | K51: =($B$18+$B$19)*'2. Cost Inputs'!$B$5 -> 0.32876712 | L51: ='2. Cost Inputs'!$B$7 -> 0.1 | M51: ='2. Cost Inputs'!$D$40 -> 100 | N51: ='2. Cost Inputs'!$D$41 -> 1500 | O51: ='2. Cost Inputs'!$D$43 -> 7500000 | P51: ='2. Cost Inputs'!$B$35 -> 0.07 | Q51: ='2. Cost Inputs'!$D$24 -> 0.3 | R51: =('2. Cost Inputs'!$B$25*($B$18+$B$20)*365*'2. Cost Inputs'!$B$5) -> 2112000 | S51: ='2. Cost Inputs'!$D$31 -> 150000 | T51: =$T$50 -> 3.8170351e-18 | U51: ='1. Technology Description'!$B$8*'1. Technology Description'!$B$9*T51*86400*1000 -> 405.08331 | V51: =U51*365*K51/1000000 -> 0.048609997 | W51: =ROUNDUP($B$22/V51,0) -> 8142 | X51: =W51*J51/1000 -> 6253.056 | Y51: =1 -> 1 | Z51: =W51*M51+X51*N51+Y51*'2. Cost Inputs'!$D$42+Y51*O51+Y51*'2. Cost Inputs'!$D$44 -> 47718784 | AA51: =Z51*(1+'2. Cost Inputs'!$B$49+'2. Cost Inputs'!$B$50+'2. Cost Inputs'!$B$52)+(W51*M51+X51*N51+Y51*'2. Cost Inputs'!$D$42)*'2. Cost Inputs'!$B$51 -> 78393811 | AB51: =(L51*(1+L51)^'2. Cost Inputs'!$B$6)/((1+L51)^'2. Cost Inputs'!$B$6-1) -> 0.13147378 | AC51: =AA51*AB51 -> 10306730 | AD51: =J51*24/1000/(U51/1000000) -> 45501.752 | AE51: =AD51*Q51*$B$22 -> 5402198.2 | AF51: =Y51*6*S51 -> 900000 | AG51: =AA51*P51 -> 5487566.8 | AH51: =R51*'2. Cost Inputs'!$D$25*Y51 -> 1900800 | AI51: =AC51+AE51+AF51+AG51+AH51+(('1. Technology Description'!$B$24/(U51/1000000)/1000)*'1. Technology Description'!$B$26*'2. Cost Inputs'!$D$28*$B$22) -> 24003525 | AJ51: =AI51/$B$22 -> 60653.223
A52: Crew cost | B52: =C52*1.4 -> 210000 | C52: ='2. Cost Inputs'!D31 -> 150000 | D52: =C52*0.7 -> 105000 | E52: $/person | F52: Annual loaded cost per crew | J52: =$D$49 -> 51.2 | K52: =($B$18+$B$19)*'2. Cost Inputs'!$B$5 -> 0.32876712 | L52: ='2. Cost Inputs'!$B$7 -> 0.1 | M52: ='2. Cost Inputs'!$D$40 -> 100 | N52: ='2. Cost Inputs'!$D$41 -> 1500 | O52: ='2. Cost Inputs'!$D$43 -> 7500000 | P52: ='2. Cost Inputs'!$B$35 -> 0.07 | Q52: ='2. Cost Inputs'!$D$24 -> 0.3 | R52: =('2. Cost Inputs'!$B$25*($B$18+$B$20)*365*'2. Cost Inputs'!$B$5) -> 2112000 | S52: ='2. Cost Inputs'!$D$31 -> 150000 | T52: =$T$50 -> 3.8170351e-18 | U52: ='1. Technology Description'!$B$8*'1. Technology Description'!$B$9*T52*86400*1000 -> 405.08331 | V52: =U52*365*K52/1000000 -> 0.048609997 | W52: =ROUNDUP($B$22/V52,0) -> 8142 | X52: =W52*J52/1000 -> 416.8704 | Y52: =1 -> 1 | Z52: =W52*M52+X52*N52+Y52*'2. Cost Inputs'!$D$42+Y52*O52+Y52*'2. Cost Inputs'!$D$44 -> 38964506 | AA52: =Z52*(1+'2. Cost Inputs'!$B$49+'2. Cost Inputs'!$B$50+'2. Cost Inputs'!$B$52)+(W52*M52+X52*N52+Y52*'2. Cost Inputs'!$D$42)*'2. Cost Inputs'!$B$51 -> 62636110 | AB52: =(L52*(1+L52)^'2. Cost Inputs'!$B$6)/((1+L52)^'2. Cost Inputs'!$B$6-1) -> 0.13147378 | AC52: =AA52*AB52 -> 8235006 | AD52: =J52*24/1000/(U52/1000000) -> 3033.4501 | AE52: =AD52*Q52*$B$22 -> 360146.54 | AF52: =Y52*6*S52 -> 900000 | AG52: =AA52*P52 -> 4384527.7 | AH52: =R52*'2. Cost Inputs'!$D$25*Y52 -> 1900800 | AI52: =AC52+AE52+AF52+AG52+AH52+(('1. Technology Description'!$B$24/(U52/1000000)/1000)*'1. Technology Description'!$B$26*'2. Cost Inputs'!$D$28*$B$22) -> 15786710 | AJ52: =AI52/$B$22 -> 39890.592
A53: Annual utilization | B53: =C53*0.6 -> 0.19726027 | C53: =($B$18+$B$19)*'2. Cost Inputs'!$B$5 -> 0.32876712 | D53: =C53*1.3 -> 0.42739726 | E53: fraction | F53: Spray-time fraction of year | J53: ='1. Technology Description'!$B$10 -> 150 | K53: =($B$18+$B$19)*'2. Cost Inputs'!$B$5 -> 0.32876712 | L53: ='2. Cost Inputs'!$B$7 -> 0.1 | M53: ='2. Cost Inputs'!$D$40 -> 100 | N53: ='2. Cost Inputs'!$D$41 -> 1500 | O53: ='2. Cost Inputs'!$D$43 -> 7500000 | P53: ='2. Cost Inputs'!$B$35 -> 0.07 | Q53: ='2. Cost Inputs'!$D$24 -> 0.3 | R53: =$B$51 -> 3168000 | S53: ='2. Cost Inputs'!$D$31 -> 150000 | T53: =PI()/6*(J53*10^-9)^3*2160 -> 3.8170351e-18 | U53: ='1. Technology Description'!$B$8*'1. Technology Description'!$B$9*T53*86400*1000 -> 405.08331 | V53: =U53*365*K53/1000000 -> 0.048609997 | W53: =ROUNDUP($B$22/V53,0) -> 8142 | X53: =W53*'1. Technology Description'!$B$17/1000 -> 4168.704 | Y53: =1 -> 1 | Z53: =W53*M53+X53*N53+Y53*'2. Cost Inputs'!$D$42+Y53*O53+Y53*'2. Cost Inputs'!$D$44 -> 44592256 | AA53: =Z53*(1+'2. Cost Inputs'!$B$49+'2. Cost Inputs'!$B$50+'2. Cost Inputs'!$B$52)+(W53*M53+X53*N53+Y53*'2. Cost Inputs'!$D$42)*'2. Cost Inputs'!$B$51 -> 72766061 | AB53: =(L53*(1+L53)^'2. Cost Inputs'!$B$6)/((1+L53)^'2. Cost Inputs'!$B$6-1) -> 0.13147378 | AC53: =AA53*AB53 -> 9566828.8 | AD53: ='1. Technology Description'!$B$17*24/1000/(U53/1000000) -> 30334.501 | AE53: =AD53*Q53*$B$22 -> 3601465.4 | AF53: =Y53*6*S53 -> 900000 | AG53: =AA53*P53 -> 5093624.3 | AH53: =R53*'2. Cost Inputs'!$D$25*Y53 -> 2851200 | AI53: =AC53+AE53+AF53+AG53+AH53+(('1. Technology Description'!$B$24/(U53/1000000)/1000)*'1. Technology Description'!$B$26*'2. Cost Inputs'!$D$28*$B$22) -> 22019348 | AJ53: =AI53/$B$22 -> 55639.512
A54: Nozzle unit cost | B54: ='2. Cost Inputs'!$H$43 -> 1000 | C54: ='2. Cost Inputs'!D40 -> 100 | D54: ='2. Cost Inputs'!$H$41 -> 10 | E54: $/nozzle | F54: Installed cost per nozzle. Worst = $1,000 scenario (tab 2 H43), base = selected scenario (D40), best = $10 scenario (H41): the full published bracket (CS-07 p.31), not a multiple of the selection. | I54: vessel fuel best | J54: ='1. Technology Description'!$B$10 -> 150 | K54: =($B$18+$B$19)*'2. Cost Inputs'!$B$5 -> 0.32876712 | L54: ='2. Cost Inputs'!$B$7 -> 0.1 | M54: ='2. Cost Inputs'!$D$40 -> 100 | N54: ='2. Cost Inputs'!$D$41 -> 1500 | O54: ='2. Cost Inputs'!$D$43 -> 7500000 | P54: ='2. Cost Inputs'!$B$35 -> 0.07 | Q54: ='2. Cost Inputs'!$D$24 -> 0.3 | R54: =$D$51 -> 1056000 | S54: ='2. Cost Inputs'!$D$31 -> 150000 | T54: =PI()/6*(J54*10^-9)^3*2160 -> 3.8170351e-18 | U54: ='1. Technology Description'!$B$8*'1. Technology Description'!$B$9*T54*86400*1000 -> 405.08331 | V54: =U54*365*K54/1000000 -> 0.048609997 | W54: =ROUNDUP($B$22/V54,0) -> 8142 | X54: =W54*'1. Technology Description'!$B$17/1000 -> 4168.704 | Y54: =1 -> 1 | Z54: =W54*M54+X54*N54+Y54*'2. Cost Inputs'!$D$42+Y54*O54+Y54*'2. Cost Inputs'!$D$44 -> 44592256 | AA54: =Z54*(1+'2. Cost Inputs'!$B$49+'2. Cost Inputs'!$B$50+'2. Cost Inputs'!$B$52)+(W54*M54+X54*N54+Y54*'2. Cost Inputs'!$D$42)*'2. Cost Inputs'!$B$51 -> 72766061 | AB54: =(L54*(1+L54)^'2. Cost Inputs'!$B$6)/((1+L54)^'2. Cost Inputs'!$B$6-1) -> 0.13147378 | AC54: =AA54*AB54 -> 9566828.8 | AD54: ='1. Technology Description'!$B$17*24/1000/(U54/1000000) -> 30334.501 | AE54: =AD54*Q54*$B$22 -> 3601465.4 | AF54: =Y54*6*S54 -> 900000 | AG54: =AA54*P54 -> 5093624.3 | AH54: =R54*'2. Cost Inputs'!$D$25*Y54 -> 950400 | AI54: =AC54+AE54+AF54+AG54+AH54+(('1. Technology Description'!$B$24/(U54/1000000)/1000)*'1. Technology Description'!$B$26*'2. Cost Inputs'!$D$28*$B$22) -> 20118548 | AJ54: =AI54/$B$22 -> 50836.483
A55: Vessel cost | B55: =C55*1.5 -> 56250000 | C55: ='2. Cost Inputs'!D43+'2. Cost Inputs'!D44 -> 37500000 | D55: =C55*0.6 -> 22500000 | E55: $/vessel | F55: Spray vessel purchase + integration, per vessel | I55: crew worst | J55: ='1. Technology Description'!$B$10 -> 150 | K55: =($B$18+$B$19)*'2. Cost Inputs'!$B$5 -> 0.32876712 | L55: ='2. Cost Inputs'!$B$7 -> 0.1 | M55: ='2. Cost Inputs'!$D$40 -> 100 | N55: ='2. Cost Inputs'!$D$41 -> 1500 | O55: ='2. Cost Inputs'!$D$43 -> 7500000 | P55: ='2. Cost Inputs'!$B$35 -> 0.07 | Q55: ='2. Cost Inputs'!$D$24 -> 0.3 | R55: =('2. Cost Inputs'!$B$25*($B$18+$B$20)*365*'2. Cost Inputs'!$B$5) -> 2112000 | S55: =$B$52 -> 210000 | T55: =PI()/6*(J55*10^-9)^3*2160 -> 3.8170351e-18 | U55: ='1. Technology Description'!$B$8*'1. Technology Description'!$B$9*T55*86400*1000 -> 405.08331 | V55: =U55*365*K55/1000000 -> 0.048609997 | W55: =ROUNDUP($B$22/V55,0) -> 8142 | X55: =W55*'1. Technology Description'!$B$17/1000 -> 4168.704 | Y55: =1 -> 1 | Z55: =W55*M55+X55*N55+Y55*'2. Cost Inputs'!$D$42+Y55*O55+Y55*'2. Cost Inputs'!$D$44 -> 44592256 | AA55: =Z55*(1+'2. Cost Inputs'!$B$49+'2. Cost Inputs'!$B$50+'2. Cost Inputs'!$B$52)+(W55*M55+X55*N55+Y55*'2. Cost Inputs'!$D$42)*'2. Cost Inputs'!$B$51 -> 72766061 | AB55: =(L55*(1+L55)^'2. Cost Inputs'!$B$6)/((1+L55)^'2. Cost Inputs'!$B$6-1) -> 0.13147378 | AC55: =AA55*AB55 -> 9566828.8 | AD55: ='1. Technology Description'!$B$17*24/1000/(U55/1000000) -> 30334.501 | AE55: =AD55*Q55*$B$22 -> 3601465.4 | AF55: =Y55*6*S55 -> 1260000 | AG55: =AA55*P55 -> 5093624.3 | AH55: =R55*'2. Cost Inputs'!$D$25*Y55 -> 1900800 | AI55: =AC55+AE55+AF55+AG55+AH55+(('1. Technology Description'!$B$24/(U55/1000000)/1000)*'1. Technology Description'!$B$26*'2. Cost Inputs'!$D$28*$B$22) -> 21428948 | AJ55: =AI55/$B$22 -> 54147.662
A56: Maintenance % | B56: =C56*1.6 -> 0.112 | C56: ='2. Cost Inputs'!B35 -> 0.07 | D56: =C56*0.5 -> 0.035 | E56: of capex/yr | F56: Maintenance + insurance rate | J56: ='1. Technology Description'!$B$10 -> 150 | K56: =($B$18+$B$19)*'2. Cost Inputs'!$B$5 -> 0.32876712 | L56: ='2. Cost Inputs'!$B$7 -> 0.1 | M56: ='2. Cost Inputs'!$D$40 -> 100 | N56: ='2. Cost Inputs'!$D$41 -> 1500 | O56: ='2. Cost Inputs'!$D$43 -> 7500000 | P56: ='2. Cost Inputs'!$B$35 -> 0.07 | Q56: ='2. Cost Inputs'!$D$24 -> 0.3 | R56: =('2. Cost Inputs'!$B$25*($B$18+$B$20)*365*'2. Cost Inputs'!$B$5) -> 2112000 | S56: =$D$52 -> 105000 | T56: =PI()/6*(J56*10^-9)^3*2160 -> 3.8170351e-18 | U56: ='1. Technology Description'!$B$8*'1. Technology Description'!$B$9*T56*86400*1000 -> 405.08331 | V56: =U56*365*K56/1000000 -> 0.048609997 | W56: =ROUNDUP($B$22/V56,0) -> 8142 | X56: =W56*'1. Technology Description'!$B$17/1000 -> 4168.704 | Y56: =1 -> 1 | Z56: =W56*M56+X56*N56+Y56*'2. Cost Inputs'!$D$42+Y56*O56+Y56*'2. Cost Inputs'!$D$44 -> 44592256 | AA56: =Z56*(1+'2. Cost Inputs'!$B$49+'2. Cost Inputs'!$B$50+'2. Cost Inputs'!$B$52)+(W56*M56+X56*N56+Y56*'2. Cost Inputs'!$D$42)*'2. Cost Inputs'!$B$51 -> 72766061 | AB56: =(L56*(1+L56)^'2. Cost Inputs'!$B$6)/((1+L56)^'2. Cost Inputs'!$B$6-1) -> 0.13147378 | AC56: =AA56*AB56 -> 9566828.8 | AD56: ='1. Technology Description'!$B$17*24/1000/(U56/1000000) -> 30334.501 | AE56: =AD56*Q56*$B$22 -> 3601465.4 | AF56: =Y56*6*S56 -> 630000 | AG56: =AA56*P56 -> 5093624.3 | AH56: =R56*'2. Cost Inputs'!$D$25*Y56 -> 1900800 | AI56: =AC56+AE56+AF56+AG56+AH56+(('1. Technology Description'!$B$24/(U56/1000000)/1000)*'1. Technology Description'!$B$26*'2. Cost Inputs'!$D$28*$B$22) -> 20798948 | AJ56: =AI56/$B$22 -> 52555.749
A57: Discount rate | B57: =C57*1.5 -> 0.15 | C57: ='2. Cost Inputs'!B7 -> 0.1 | D57: =C57*0.6 -> 0.06 | E57: fraction | F57: Cost of capital | I57: util worst | J57: ='1. Technology Description'!$B$10 -> 150 | K57: =$B$53 -> 0.19726027 | L57: ='2. Cost Inputs'!$B$7 -> 0.1 | M57: ='2. Cost Inputs'!$D$40 -> 100 | N57: ='2. Cost Inputs'!$D$41 -> 1500 | O57: ='2. Cost Inputs'!$D$43 -> 7500000 | P57: ='2. Cost Inputs'!$B$35 -> 0.07 | Q57: ='2. Cost Inputs'!$D$24 -> 0.3 | R57: =('2. Cost Inputs'!$B$25*($B$18+$B$20)*365*'2. Cost Inputs'!$B$5) -> 2112000 | S57: ='2. Cost Inputs'!$D$31 -> 150000 | T57: =PI()/6*(J57*10^-9)^3*2160 -> 3.8170351e-18 | U57: ='1. Technology Description'!$B$8*'1. Technology Description'!$B$9*T57*86400*1000 -> 405.08331 | V57: =U57*365*K57/1000000 -> 0.029165998 | W57: =ROUNDUP($B$22/V57,0) -> 13569 | X57: =W57*'1. Technology Description'!$B$17/1000 -> 6947.328 | Y57: =1 -> 1 | Z57: =W57*M57+X57*N57+Y57*'2. Cost Inputs'!$D$42+Y57*O57+Y57*'2. Cost Inputs'!$D$44 -> 49302892 | AA57: =Z57*(1+'2. Cost Inputs'!$B$49+'2. Cost Inputs'!$B$50+'2. Cost Inputs'!$B$52)+(W57*M57+X57*N57+Y57*'2. Cost Inputs'!$D$42)*'2. Cost Inputs'!$B$51 -> 81245206 | AB57: =(L57*(1+L57)^'2. Cost Inputs'!$B$6)/((1+L57)^'2. Cost Inputs'!$B$6-1) -> 0.13147378 | AC57: =AA57*AB57 -> 10681614 | AD57: ='1. Technology Description'!$B$17*24/1000/(U57/1000000) -> 30334.501 | AE57: =AD57*Q57*$B$22 -> 3601465.4 | AF57: =Y57*6*S57 -> 900000 | AG57: =AA57*P57 -> 5687164.4 | AH57: =R57*'2. Cost Inputs'!$D$25*Y57 -> 1900800 | AI57: =AC57+AE57+AF57+AG57+AH57+(('1. Technology Description'!$B$24/(U57/1000000)/1000)*'1. Technology Description'!$B$26*'2. Cost Inputs'!$D$28*$B$22) -> 22777273 | AJ57: =AI57/$B$22 -> 57554.673
A58: Energy price | B58: =C58*1.5 -> 0.45 | C58: ='2. Cost Inputs'!D24 -> 0.3 | D58: =C58*0.6 -> 0.18 | E58: $/kWh | F58: Marine diesel price | I58: util best | J58: ='1. Technology Description'!$B$10 -> 150 | K58: =$D$53 -> 0.42739726 | L58: ='2. Cost Inputs'!$B$7 -> 0.1 | M58: ='2. Cost Inputs'!$D$40 -> 100 | N58: ='2. Cost Inputs'!$D$41 -> 1500 | O58: ='2. Cost Inputs'!$D$43 -> 7500000 | P58: ='2. Cost Inputs'!$B$35 -> 0.07 | Q58: ='2. Cost Inputs'!$D$24 -> 0.3 | R58: =('2. Cost Inputs'!$B$25*($B$18+$B$20)*365*'2. Cost Inputs'!$B$5) -> 2112000 | S58: ='2. Cost Inputs'!$D$31 -> 150000 | T58: =PI()/6*(J58*10^-9)^3*2160 -> 3.8170351e-18 | U58: ='1. Technology Description'!$B$8*'1. Technology Description'!$B$9*T58*86400*1000 -> 405.08331 | V58: =U58*365*K58/1000000 -> 0.063192996 | W58: =ROUNDUP($B$22/V58,0) -> 6263 | X58: =W58*'1. Technology Description'!$B$17/1000 -> 3206.656 | Y58: =1 -> 1 | Z58: =W58*M58+X58*N58+Y58*'2. Cost Inputs'!$D$42+Y58*O58+Y58*'2. Cost Inputs'!$D$44 -> 42961284 | AA58: =Z58*(1+'2. Cost Inputs'!$B$49+'2. Cost Inputs'!$B$50+'2. Cost Inputs'!$B$52)+(W58*M58+X58*N58+Y58*'2. Cost Inputs'!$D$42)*'2. Cost Inputs'!$B$51 -> 69830311 | AB58: =(L58*(1+L58)^'2. Cost Inputs'!$B$6)/((1+L58)^'2. Cost Inputs'!$B$6-1) -> 0.13147378 | AC58: =AA58*AB58 -> 9180854.8 | AD58: ='1. Technology Description'!$B$17*24/1000/(U58/1000000) -> 30334.501 | AE58: =AD58*Q58*$B$22 -> 3601465.4 | AF58: =Y58*6*S58 -> 900000 | AG58: =AA58*P58 -> 4888121.8 | AH58: =R58*'2. Cost Inputs'!$D$25*Y58 -> 1900800 | AI58: =AC58+AE58+AF58+AG58+AH58+(('1. Technology Description'!$B$24/(U58/1000000)/1000)*'1. Technology Description'!$B$26*'2. Cost Inputs'!$D$28*$B$22) -> 20477471 | AJ58: =AI58/$B$22 -> 51743.427
A59: Compressor $/kW | B59: =C59*1.5 -> 2250 | C59: ='2. Cost Inputs'!D41 -> 1500 | D59: =C59*0.6 -> 900 | E59: $/kW | F59: HP compressor + genset | I59: nozzle cost worst | J59: ='1. Technology Description'!$B$10 -> 150 | K59: =($B$18+$B$19)*'2. Cost Inputs'!$B$5 -> 0.32876712 | L59: ='2. Cost Inputs'!$B$7 -> 0.1 | M59: =$B$54 -> 1000 | N59: ='2. Cost Inputs'!$D$41 -> 1500 | O59: ='2. Cost Inputs'!$D$43 -> 7500000 | P59: ='2. Cost Inputs'!$B$35 -> 0.07 | Q59: ='2. Cost Inputs'!$D$24 -> 0.3 | R59: =('2. Cost Inputs'!$B$25*($B$18+$B$20)*365*'2. Cost Inputs'!$B$5) -> 2112000 | S59: ='2. Cost Inputs'!$D$31 -> 150000 | T59: =PI()/6*(J59*10^-9)^3*2160 -> 3.8170351e-18 | U59: ='1. Technology Description'!$B$8*'1. Technology Description'!$B$9*T59*86400*1000 -> 405.08331 | V59: =U59*365*K59/1000000 -> 0.048609997 | W59: =ROUNDUP($B$22/V59,0) -> 8142 | X59: =W59*'1. Technology Description'!$B$17/1000 -> 4168.704 | Y59: =1 -> 1 | Z59: =W59*M59+X59*N59+Y59*'2. Cost Inputs'!$D$42+Y59*O59+Y59*'2. Cost Inputs'!$D$44 -> 51920056 | AA59: =Z59*(1+'2. Cost Inputs'!$B$49+'2. Cost Inputs'!$B$50+'2. Cost Inputs'!$B$52)+(W59*M59+X59*N59+Y59*'2. Cost Inputs'!$D$42)*'2. Cost Inputs'!$B$51 -> 85956101 | AB59: =(L59*(1+L59)^'2. Cost Inputs'!$B$6)/((1+L59)^'2. Cost Inputs'!$B$6-1) -> 0.13147378 | AC59: =AA59*AB59 -> 11300973 | AD59: ='1. Technology Description'!$B$17*24/1000/(U59/1000000) -> 30334.501 | AE59: =AD59*Q59*$B$22 -> 3601465.4 | AF59: =Y59*6*S59 -> 900000 | AG59: =AA59*P59 -> 6016927.1 | AH59: =R59*'2. Cost Inputs'!$D$25*Y59 -> 1900800 | AI59: =AC59+AE59+AF59+AG59+AH59+(('1. Technology Description'!$B$24/(U59/1000000)/1000)*'1. Technology Description'!$B$26*'2. Cost Inputs'!$D$28*$B$22) -> 23726395 | AJ59: =AI59/$B$22 -> 59952.959
J60: ='1. Technology Description'!$B$10 -> 150 | K60: =($B$18+$B$19)*'2. Cost Inputs'!$B$5 -> 0.32876712 | L60: ='2. Cost Inputs'!$B$7 -> 0.1 | M60: =$D$54 -> 10 | N60: ='2. Cost Inputs'!$D$41 -> 1500 | O60: ='2. Cost Inputs'!$D$43 -> 7500000 | P60: ='2. Cost Inputs'!$B$35 -> 0.07 | Q60: ='2. Cost Inputs'!$D$24 -> 0.3 | R60: =('2. Cost Inputs'!$B$25*($B$18+$B$20)*365*'2. Cost Inputs'!$B$5) -> 2112000 | S60: ='2. Cost Inputs'!$D$31 -> 150000 | T60: =PI()/6*(J60*10^-9)^3*2160 -> 3.8170351e-18 | U60: ='1. Technology Description'!$B$8*'1. Technology Description'!$B$9*T60*86400*1000 -> 405.08331 | V60: =U60*365*K60/1000000 -> 0.048609997 | W60: =ROUNDUP($B$22/V60,0) -> 8142 | X60: =W60*'1. Technology Description'!$B$17/1000 -> 4168.704 | Y60: =1 -> 1 | Z60: =W60*M60+X60*N60+Y60*'2. Cost Inputs'!$D$42+Y60*O60+Y60*'2. Cost Inputs'!$D$44 -> 43859476 | AA60: =Z60*(1+'2. Cost Inputs'!$B$49+'2. Cost Inputs'!$B$50+'2. Cost Inputs'!$B$52)+(W60*M60+X60*N60+Y60*'2. Cost Inputs'!$D$42)*'2. Cost Inputs'!$B$51 -> 71447057 | AB60: =(L60*(1+L60)^'2. Cost Inputs'!$B$6)/((1+L60)^'2. Cost Inputs'!$B$6-1) -> 0.13147378 | AC60: =AA60*AB60 -> 9393414.4 | AD60: ='1. Technology Description'!$B$17*24/1000/(U60/1000000) -> 30334.501 | AE60: =AD60*Q60*$B$22 -> 3601465.4 | AF60: =Y60*6*S60 -> 900000 | AG60: =AA60*P60 -> 5001294 | AH60: =R60*'2. Cost Inputs'!$D$25*Y60 -> 1900800 | AI60: =AC60+AE60+AF60+AG60+AH60+(('1. Technology Description'!$B$24/(U60/1000000)/1000)*'1. Technology Description'!$B$26*'2. Cost Inputs'!$D$28*$B$22) -> 20803203 | AJ60: =AI60/$B$22 -> 52566.501
I61: vessel cost worst | J61: ='1. Technology Description'!$B$10 -> 150 | K61: =($B$18+$B$19)*'2. Cost Inputs'!$B$5 -> 0.32876712 | L61: ='2. Cost Inputs'!$B$7 -> 0.1 | M61: ='2. Cost Inputs'!$D$40 -> 100 | N61: ='2. Cost Inputs'!$D$41 -> 1500 | O61: =$B$55 -> 56250000 | P61: ='2. Cost Inputs'!$B$35 -> 0.07 | Q61: ='2. Cost Inputs'!$D$24 -> 0.3 | R61: =('2. Cost Inputs'!$B$25*($B$18+$B$20)*365*'2. Cost Inputs'!$B$5) -> 2112000 | S61: ='2. Cost Inputs'!$D$31 -> 150000 | T61: =PI()/6*(J61*10^-9)^3*2160 -> 3.8170351e-18 | U61: ='1. Technology Description'!$B$8*'1. Technology Description'!$B$9*T61*86400*1000 -> 405.08331 | V61: =U61*365*K61/1000000 -> 0.048609997 | W61: =ROUNDUP($B$22/V61,0) -> 8142 | X61: =W61*'1. Technology Description'!$B$17/1000 -> 4168.704 | Y61: =1 -> 1 | Z61: =W61*M61+X61*N61+Y61*'2. Cost Inputs'!$D$42+Y61*O61 -> 63342256 | AA61: =Z61*(1+'2. Cost Inputs'!$B$49+'2. Cost Inputs'!$B$50+'2. Cost Inputs'!$B$52)+(W61*M61+X61*N61+Y61*'2. Cost Inputs'!$D$42)*'2. Cost Inputs'!$B$51 -> 1.0276606e+08 | AB61: =(L61*(1+L61)^'2. Cost Inputs'!$B$6)/((1+L61)^'2. Cost Inputs'!$B$6-1) -> 0.13147378 | AC61: =AA61*AB61 -> 13511042 | AD61: ='1. Technology Description'!$B$17*24/1000/(U61/1000000) -> 30334.501 | AE61: =AD61*Q61*$B$22 -> 3601465.4 | AF61: =Y61*6*S61 -> 900000 | AG61: =AA61*P61 -> 7193624.3 | AH61: =R61*'2. Cost Inputs'!$D$25*Y61 -> 1900800 | AI61: =AC61+AE61+AF61+AG61+AH61+(('1. Technology Description'!$B$24/(U61/1000000)/1000)*'1. Technology Description'!$B$26*'2. Cost Inputs'!$D$28*$B$22) -> 27113161 | AJ61: =AI61/$B$22 -> 68510.797
A62: Tornado chart data (helper) | I62: vessel cost best | J62: ='1. Technology Description'!$B$10 -> 150 | K62: =($B$18+$B$19)*'2. Cost Inputs'!$B$5 -> 0.32876712 | L62: ='2. Cost Inputs'!$B$7 -> 0.1 | M62: ='2. Cost Inputs'!$D$40 -> 100 | N62: ='2. Cost Inputs'!$D$41 -> 1500 | O62: =$D$55 -> 22500000 | P62: ='2. Cost Inputs'!$B$35 -> 0.07 | Q62: ='2. Cost Inputs'!$D$24 -> 0.3 | R62: =('2. Cost Inputs'!$B$25*($B$18+$B$20)*365*'2. Cost Inputs'!$B$5) -> 2112000 | S62: ='2. Cost Inputs'!$D$31 -> 150000 | T62: =PI()/6*(J62*10^-9)^3*2160 -> 3.8170351e-18 | U62: ='1. Technology Description'!$B$8*'1. Technology Description'!$B$9*T62*86400*1000 -> 405.08331 | V62: =U62*365*K62/1000000 -> 0.048609997 | W62: =ROUNDUP($B$22/V62,0) -> 8142 | X62: =W62*'1. Technology Description'!$B$17/1000 -> 4168.704 | Y62: =1 -> 1 | Z62: =W62*M62+X62*N62+Y62*'2. Cost Inputs'!$D$42+Y62*O62 -> 29592256 | AA62: =Z62*(1+'2. Cost Inputs'!$B$49+'2. Cost Inputs'!$B$50+'2. Cost Inputs'!$B$52)+(W62*M62+X62*N62+Y62*'2. Cost Inputs'!$D$42)*'2. Cost Inputs'!$B$51 -> 48766061 | AB62: =(L62*(1+L62)^'2. Cost Inputs'!$B$6)/((1+L62)^'2. Cost Inputs'!$B$6-1) -> 0.13147378 | AC62: =AA62*AB62 -> 6411458.2 | AD62: ='1. Technology Description'!$B$17*24/1000/(U62/1000000) -> 30334.501 | AE62: =AD62*Q62*$B$22 -> 3601465.4 | AF62: =Y62*6*S62 -> 900000 | AG62: =AA62*P62 -> 3413624.3 | AH62: =R62*'2. Cost Inputs'!$D$25*Y62 -> 1900800 | AI62: =AC62+AE62+AF62+AG62+AH62+(('1. Technology Description'!$B$24/(U62/1000000)/1000)*'1. Technology Description'!$B$26*'2. Cost Inputs'!$D$28*$B$22) -> 16233577 | AJ62: =AI62/$B$22 -> 41019.758
A63: Variable | B63: spacer (hidden) | C63: cost-reducing span | D63: cost-raising span | E63: max (label helper) | I63: maint worst | J63: ='1. Technology Description'!$B$10 -> 150 | K63: =($B$18+$B$19)*'2. Cost Inputs'!$B$5 -> 0.32876712 | L63: ='2. Cost Inputs'!$B$7 -> 0.1 | M63: ='2. Cost Inputs'!$D$40 -> 100 | N63: ='2. Cost Inputs'!$D$41 -> 1500 | O63: ='2. Cost Inputs'!$D$43 -> 7500000 | P63: =$B$56 -> 0.112 | Q63: ='2. Cost Inputs'!$D$24 -> 0.3 | R63: =('2. Cost Inputs'!$B$25*($B$18+$B$20)*365*'2. Cost Inputs'!$B$5) -> 2112000 | S63: ='2. Cost Inputs'!$D$31 -> 150000 | T63: =PI()/6*(J63*10^-9)^3*2160 -> 3.8170351e-18 | U63: ='1. Technology Description'!$B$8*'1. Technology Description'!$B$9*T63*86400*1000 -> 405.08331 | V63: =U63*365*K63/1000000 -> 0.048609997 | W63: =ROUNDUP($B$22/V63,0) -> 8142 | X63: =W63*'1. Technology Description'!$B$17/1000 -> 4168.704 | Y63: =1 -> 1 | Z63: =W63*M63+X63*N63+Y63*'2. Cost Inputs'!$D$42+Y63*O63+Y63*'2. Cost Inputs'!$D$44 -> 44592256 | AA63: =Z63*(1+'2. Cost Inputs'!$B$49+'2. Cost Inputs'!$B$50+'2. Cost Inputs'!$B$52)+(W63*M63+X63*N63+Y63*'2. Cost Inputs'!$D$42)*'2. Cost Inputs'!$B$51 -> 72766061 | AB63: =(L63*(1+L63)^'2. Cost Inputs'!$B$6)/((1+L63)^'2. Cost Inputs'!$B$6-1) -> 0.13147378 | AC63: =AA63*AB63 -> 9566828.8 | AD63: ='1. Technology Description'!$B$17*24/1000/(U63/1000000) -> 30334.501 | AE63: =AD63*Q63*$B$22 -> 3601465.4 | AF63: =Y63*6*S63 -> 900000 | AG63: =AA63*P63 -> 8149798.8 | AH63: =R63*'2. Cost Inputs'!$D$25*Y63 -> 1900800 | AI63: =AC63+AE63+AF63+AG63+AH63+(('1. Technology Description'!$B$24/(U63/1000000)/1000)*'1. Technology Description'!$B$26*'2. Cost Inputs'!$D$28*$B$22) -> 24125123 | AJ63: =AI63/$B$22 -> 60960.481
A64: Compressor $/kW | B64: =MIN(AJ69,AJ70) -> 50945.957 | C64: =$AJ$50-MIN(AJ69,AJ70) -> 2292.0401 | D64: =MAX(AJ69,AJ70)-$AJ$50 -> 2865.0501 | E64: =MAX(AJ69,AJ70) -> 56103.048 | I64: maint best | J64: ='1. Technology Description'!$B$10 -> 150 | K64: =($B$18+$B$19)*'2. Cost Inputs'!$B$5 -> 0.32876712 | L64: ='2. Cost Inputs'!$B$7 -> 0.1 | M64: ='2. Cost Inputs'!$D$40 -> 100 | N64: ='2. Cost Inputs'!$D$41 -> 1500 | O64: ='2. Cost Inputs'!$D$43 -> 7500000 | P64: =$D$56 -> 0.035 | Q64: ='2. Cost Inputs'!$D$24 -> 0.3 | R64: =('2. Cost Inputs'!$B$25*($B$18+$B$20)*365*'2. Cost Inputs'!$B$5) -> 2112000 | S64: ='2. Cost Inputs'!$D$31 -> 150000 | T64: =PI()/6*(J64*10^-9)^3*2160 -> 3.8170351e-18 | U64: ='1. Technology Description'!$B$8*'1. Technology Description'!$B$9*T64*86400*1000 -> 405.08331 | V64: =U64*365*K64/1000000 -> 0.048609997 | W64: =ROUNDUP($B$22/V64,0) -> 8142 | X64: =W64*'1. Technology Description'!$B$17/1000 -> 4168.704 | Y64: =1 -> 1 | Z64: =W64*M64+X64*N64+Y64*'2. Cost Inputs'!$D$42+Y64*O64+Y64*'2. Cost Inputs'!$D$44 -> 44592256 | AA64: =Z64*(1+'2. Cost Inputs'!$B$49+'2. Cost Inputs'!$B$50+'2. Cost Inputs'!$B$52)+(W64*M64+X64*N64+Y64*'2. Cost Inputs'!$D$42)*'2. Cost Inputs'!$B$51 -> 72766061 | AB64: =(L64*(1+L64)^'2. Cost Inputs'!$B$6)/((1+L64)^'2. Cost Inputs'!$B$6-1) -> 0.13147378 | AC64: =AA64*AB64 -> 9566828.8 | AD64: ='1. Technology Description'!$B$17*24/1000/(U64/1000000) -> 30334.501 | AE64: =AD64*Q64*$B$22 -> 3601465.4 | AF64: =Y64*6*S64 -> 900000 | AG64: =AA64*P64 -> 2546812.1 | AH64: =R64*'2. Cost Inputs'!$D$25*Y64 -> 1900800 | AI64: =AC64+AE64+AF64+AG64+AH64+(('1. Technology Description'!$B$24/(U64/1000000)/1000)*'1. Technology Description'!$B$26*'2. Cost Inputs'!$D$28*$B$22) -> 18522136 | AJ64: =AI64/$B$22 -> 46802.594
A65: Energy price | B65: =MIN(AJ67,AJ68) -> 49597.857 | C65: =$AJ$50-MIN(AJ67,AJ68) -> 3640.1401 | D65: =MAX(AJ67,AJ68)-$AJ$50 -> 4550.1752 | E65: =MAX(AJ67,AJ68) -> 57788.173 | I65: disc worst | J65: ='1. Technology Description'!$B$10 -> 150 | K65: =($B$18+$B$19)*'2. Cost Inputs'!$B$5 -> 0.32876712 | L65: =$B$57 -> 0.15 | M65: ='2. Cost Inputs'!$D$40 -> 100 | N65: ='2. Cost Inputs'!$D$41 -> 1500 | O65: ='2. Cost Inputs'!$D$43 -> 7500000 | P65: ='2. Cost Inputs'!$B$35 -> 0.07 | Q65: ='2. Cost Inputs'!$D$24 -> 0.3 | R65: =('2. Cost Inputs'!$B$25*($B$18+$B$20)*365*'2. Cost Inputs'!$B$5) -> 2112000 | S65: ='2. Cost Inputs'!$D$31 -> 150000 | T65: =PI()/6*(J65*10^-9)^3*2160 -> 3.8170351e-18 | U65: ='1. Technology Description'!$B$8*'1. Technology Description'!$B$9*T65*86400*1000 -> 405.08331 | V65: =U65*365*K65/1000000 -> 0.048609997 | W65: =ROUNDUP($B$22/V65,0) -> 8142 | X65: =W65*'1. Technology Description'!$B$17/1000 -> 4168.704 | Y65: =1 -> 1 | Z65: =W65*M65+X65*N65+Y65*'2. Cost Inputs'!$D$42+Y65*O65+Y65*'2. Cost Inputs'!$D$44 -> 44592256 | AA65: =Z65*(1+'2. Cost Inputs'!$B$49+'2. Cost Inputs'!$B$50+'2. Cost Inputs'!$B$52)+(W65*M65+X65*N65+Y65*'2. Cost Inputs'!$D$42)*'2. Cost Inputs'!$B$51 -> 72766061 | AB65: =(L65*(1+L65)^'2. Cost Inputs'!$B$6)/((1+L65)^'2. Cost Inputs'!$B$6-1) -> 0.17101705 | AC65: =AA65*AB65 -> 12444237 | AD65: ='1. Technology Description'!$B$17*24/1000/(U65/1000000) -> 30334.501 | AE65: =AD65*Q65*$B$22 -> 3601465.4 | AF65: =Y65*6*S65 -> 900000 | AG65: =AA65*P65 -> 5093624.3 | AH65: =R65*'2. Cost Inputs'!$D$25*Y65 -> 1900800 | AI65: =AC65+AE65+AF65+AG65+AH65+(('1. Technology Description'!$B$24/(U65/1000000)/1000)*'1. Technology Description'!$B$26*'2. Cost Inputs'!$D$28*$B$22) -> 23946356 | AJ65: =AI65/$B$22 -> 60508.767
A66: Discount rate | B66: =MIN(AJ65,AJ66) -> 47995.716 | C66: =$AJ$50-MIN(AJ65,AJ66) -> 5242.2819 | D66: =MAX(AJ65,AJ66)-$AJ$50 -> 7270.7694 | E66: =MAX(AJ65,AJ66) -> 60508.767 | I66: disc best | J66: ='1. Technology Description'!$B$10 -> 150 | K66: =($B$18+$B$19)*'2. Cost Inputs'!$B$5 -> 0.32876712 | L66: =$D$57 -> 0.06 | M66: ='2. Cost Inputs'!$D$40 -> 100 | N66: ='2. Cost Inputs'!$D$41 -> 1500 | O66: ='2. Cost Inputs'!$D$43 -> 7500000 | P66: ='2. Cost Inputs'!$B$35 -> 0.07 | Q66: ='2. Cost Inputs'!$D$24 -> 0.3 | R66: =('2. Cost Inputs'!$B$25*($B$18+$B$20)*365*'2. Cost Inputs'!$B$5) -> 2112000 | S66: ='2. Cost Inputs'!$D$31 -> 150000 | T66: =PI()/6*(J66*10^-9)^3*2160 -> 3.8170351e-18 | U66: ='1. Technology Description'!$B$8*'1. Technology Description'!$B$9*T66*86400*1000 -> 405.08331 | V66: =U66*365*K66/1000000 -> 0.048609997 | W66: =ROUNDUP($B$22/V66,0) -> 8142 | X66: =W66*'1. Technology Description'!$B$17/1000 -> 4168.704 | Y66: =1 -> 1 | Z66: =W66*M66+X66*N66+Y66*'2. Cost Inputs'!$D$42+Y66*O66+Y66*'2. Cost Inputs'!$D$44 -> 44592256 | AA66: =Z66*(1+'2. Cost Inputs'!$B$49+'2. Cost Inputs'!$B$50+'2. Cost Inputs'!$B$52)+(W66*M66+X66*N66+Y66*'2. Cost Inputs'!$D$42)*'2. Cost Inputs'!$B$51 -> 72766061 | AB66: =(L66*(1+L66)^'2. Cost Inputs'!$B$6)/((1+L66)^'2. Cost Inputs'!$B$6-1) -> 0.10296276 | AC66: =AA66*AB66 -> 7492194.7 | AD66: ='1. Technology Description'!$B$17*24/1000/(U66/1000000) -> 30334.501 | AE66: =AD66*Q66*$B$22 -> 3601465.4 | AF66: =Y66*6*S66 -> 900000 | AG66: =AA66*P66 -> 5093624.3 | AH66: =R66*'2. Cost Inputs'!$D$25*Y66 -> 1900800 | AI66: =AC66+AE66+AF66+AG66+AH66+(('1. Technology Description'!$B$24/(U66/1000000)/1000)*'1. Technology Description'!$B$26*'2. Cost Inputs'!$D$28*$B$22) -> 18994314 | AJ66: =AI66/$B$22 -> 47995.716
A67: Maintenance % | B67: =MIN(AJ63,AJ64) -> 46802.594 | C67: =$AJ$50-MIN(AJ63,AJ64) -> 6435.4033 | D67: =MAX(AJ63,AJ64)-$AJ$50 -> 7722.484 | E67: =MAX(AJ63,AJ64) -> 60960.481 | I67: energy price worst | J67: ='1. Technology Description'!$B$10 -> 150 | K67: =($B$18+$B$19)*'2. Cost Inputs'!$B$5 -> 0.32876712 | L67: ='2. Cost Inputs'!$B$7 -> 0.1 | M67: ='2. Cost Inputs'!$D$40 -> 100 | N67: ='2. Cost Inputs'!$D$41 -> 1500 | O67: ='2. Cost Inputs'!$D$43 -> 7500000 | P67: ='2. Cost Inputs'!$B$35 -> 0.07 | Q67: =$B$58 -> 0.45 | R67: =('2. Cost Inputs'!$B$25*($B$18+$B$20)*365*'2. Cost Inputs'!$B$5) -> 2112000 | S67: ='2. Cost Inputs'!$D$31 -> 150000 | T67: =PI()/6*(J67*10^-9)^3*2160 -> 3.8170351e-18 | U67: ='1. Technology Description'!$B$8*'1. Technology Description'!$B$9*T67*86400*1000 -> 405.08331 | V67: =U67*365*K67/1000000 -> 0.048609997 | W67: =ROUNDUP($B$22/V67,0) -> 8142 | X67: =W67*'1. Technology Description'!$B$17/1000 -> 4168.704 | Y67: =1 -> 1 | Z67: =W67*M67+X67*N67+Y67*'2. Cost Inputs'!$D$42+Y67*O67+Y67*'2. Cost Inputs'!$D$44 -> 44592256 | AA67: =Z67*(1+'2. Cost Inputs'!$B$49+'2. Cost Inputs'!$B$50+'2. Cost Inputs'!$B$52)+(W67*M67+X67*N67+Y67*'2. Cost Inputs'!$D$42)*'2. Cost Inputs'!$B$51 -> 72766061 | AB67: =(L67*(1+L67)^'2. Cost Inputs'!$B$6)/((1+L67)^'2. Cost Inputs'!$B$6-1) -> 0.13147378 | AC67: =AA67*AB67 -> 9566828.8 | AD67: ='1. Technology Description'!$B$17*24/1000/(U67/1000000) -> 30334.501 | AE67: =AD67*Q67*$B$22 -> 5402198.2 | AF67: =Y67*6*S67 -> 900000 | AG67: =AA67*P67 -> 5093624.3 | AH67: =R67*'2. Cost Inputs'!$D$25*Y67 -> 1900800 | AI67: =AC67+AE67+AF67+AG67+AH67+(('1. Technology Description'!$B$24/(U67/1000000)/1000)*'1. Technology Description'!$B$26*'2. Cost Inputs'!$D$28*$B$22) -> 22869681 | AJ67: =AI67/$B$22 -> 57788.173
A68: Vessel cost | B68: =MIN(AJ61,AJ62) -> 41019.758 | C68: =$AJ$50-MIN(AJ61,AJ62) -> 12218.239 | D68: =MAX(AJ61,AJ62)-$AJ$50 -> 15272.799 | E68: =MAX(AJ61,AJ62) -> 68510.797 | I68: energy price best | J68: ='1. Technology Description'!$B$10 -> 150 | K68: =($B$18+$B$19)*'2. Cost Inputs'!$B$5 -> 0.32876712 | L68: ='2. Cost Inputs'!$B$7 -> 0.1 | M68: ='2. Cost Inputs'!$D$40 -> 100 | N68: ='2. Cost Inputs'!$D$41 -> 1500 | O68: ='2. Cost Inputs'!$D$43 -> 7500000 | P68: ='2. Cost Inputs'!$B$35 -> 0.07 | Q68: =$D$58 -> 0.18 | R68: =('2. Cost Inputs'!$B$25*($B$18+$B$20)*365*'2. Cost Inputs'!$B$5) -> 2112000 | S68: ='2. Cost Inputs'!$D$31 -> 150000 | T68: =PI()/6*(J68*10^-9)^3*2160 -> 3.8170351e-18 | U68: ='1. Technology Description'!$B$8*'1. Technology Description'!$B$9*T68*86400*1000 -> 405.08331 | V68: =U68*365*K68/1000000 -> 0.048609997 | W68: =ROUNDUP($B$22/V68,0) -> 8142 | X68: =W68*'1. Technology Description'!$B$17/1000 -> 4168.704 | Y68: =1 -> 1 | Z68: =W68*M68+X68*N68+Y68*'2. Cost Inputs'!$D$42+Y68*O68+Y68*'2. Cost Inputs'!$D$44 -> 44592256 | AA68: =Z68*(1+'2. Cost Inputs'!$B$49+'2. Cost Inputs'!$B$50+'2. Cost Inputs'!$B$52)+(W68*M68+X68*N68+Y68*'2. Cost Inputs'!$D$42)*'2. Cost Inputs'!$B$51 -> 72766061 | AB68: =(L68*(1+L68)^'2. Cost Inputs'!$B$6)/((1+L68)^'2. Cost Inputs'!$B$6-1) -> 0.13147378 | AC68: =AA68*AB68 -> 9566828.8 | AD68: ='1. Technology Description'!$B$17*24/1000/(U68/1000000) -> 30334.501 | AE68: =AD68*Q68*$B$22 -> 2160879.3 | AF68: =Y68*6*S68 -> 900000 | AG68: =AA68*P68 -> 5093624.3 | AH68: =R68*'2. Cost Inputs'!$D$25*Y68 -> 1900800 | AI68: =AC68+AE68+AF68+AG68+AH68+(('1. Technology Description'!$B$24/(U68/1000000)/1000)*'1. Technology Description'!$B$26*'2. Cost Inputs'!$D$28*$B$22) -> 19628362 | AJ68: =AI68/$B$22 -> 49597.857
A69: Nozzle unit cost | B69: =MIN(AJ59,AJ60) -> 52566.501 | C69: =$AJ$50-MIN(AJ59,AJ60) -> 671.49611 | D69: =MAX(AJ59,AJ60)-$AJ$50 -> 6714.9611 | E69: =MAX(AJ59,AJ60) -> 59952.959 | I69: compressor worst | J69: ='1. Technology Description'!$B$10 -> 150 | K69: =($B$18+$B$19)*'2. Cost Inputs'!$B$5 -> 0.32876712 | L69: ='2. Cost Inputs'!$B$7 -> 0.1 | M69: ='2. Cost Inputs'!$D$40 -> 100 | N69: =$B$59 -> 2250 | O69: ='2. Cost Inputs'!$D$43 -> 7500000 | P69: ='2. Cost Inputs'!$B$35 -> 0.07 | Q69: ='2. Cost Inputs'!$D$24 -> 0.3 | R69: =('2. Cost Inputs'!$B$25*($B$18+$B$20)*365*'2. Cost Inputs'!$B$5) -> 2112000 | S69: ='2. Cost Inputs'!$D$31 -> 150000 | T69: =PI()/6*(J69*10^-9)^3*2160 -> 3.8170351e-18 | U69: ='1. Technology Description'!$B$8*'1. Technology Description'!$B$9*T69*86400*1000 -> 405.08331 | V69: =U69*365*K69/1000000 -> 0.048609997 | W69: =ROUNDUP($B$22/V69,0) -> 8142 | X69: =W69*'1. Technology Description'!$B$17/1000 -> 4168.704 | Y69: =1 -> 1 | Z69: =W69*M69+X69*N69+Y69*'2. Cost Inputs'!$D$42+Y69*O69+Y69*'2. Cost Inputs'!$D$44 -> 47718784 | AA69: =Z69*(1+'2. Cost Inputs'!$B$49+'2. Cost Inputs'!$B$50+'2. Cost Inputs'!$B$52)+(W69*M69+X69*N69+Y69*'2. Cost Inputs'!$D$42)*'2. Cost Inputs'!$B$51 -> 78393811 | AB69: =(L69*(1+L69)^'2. Cost Inputs'!$B$6)/((1+L69)^'2. Cost Inputs'!$B$6-1) -> 0.13147378 | AC69: =AA69*AB69 -> 10306730 | AD69: ='1. Technology Description'!$B$17*24/1000/(U69/1000000) -> 30334.501 | AE69: =AD69*Q69*$B$22 -> 3601465.4 | AF69: =Y69*6*S69 -> 900000 | AG69: =AA69*P69 -> 5487566.8 | AH69: =R69*'2. Cost Inputs'!$D$25*Y69 -> 1900800 | AI69: =AC69+AE69+AF69+AG69+AH69+(('1. Technology Description'!$B$24/(U69/1000000)/1000)*'1. Technology Description'!$B$26*'2. Cost Inputs'!$D$28*$B$22) -> 22202792 | AJ69: =AI69/$B$22 -> 56103.048
A70: Annual utilization | B70: =MIN(AJ57,AJ58) -> 51743.427 | C70: =$AJ$50-MIN(AJ57,AJ58) -> 1494.5705 | D70: =MAX(AJ57,AJ58)-$AJ$50 -> 4316.6759 | E70: =MAX(AJ57,AJ58) -> 57554.673 | I70: compressor best | J70: ='1. Technology Description'!$B$10 -> 150 | K70: =($B$18+$B$19)*'2. Cost Inputs'!$B$5 -> 0.32876712 | L70: ='2. Cost Inputs'!$B$7 -> 0.1 | M70: ='2. Cost Inputs'!$D$40 -> 100 | N70: =$D$59 -> 900 | O70: ='2. Cost Inputs'!$D$43 -> 7500000 | P70: ='2. Cost Inputs'!$B$35 -> 0.07 | Q70: ='2. Cost Inputs'!$D$24 -> 0.3 | R70: =('2. Cost Inputs'!$B$25*($B$18+$B$20)*365*'2. Cost Inputs'!$B$5) -> 2112000 | S70: ='2. Cost Inputs'!$D$31 -> 150000 | T70: =PI()/6*(J70*10^-9)^3*2160 -> 3.8170351e-18 | U70: ='1. Technology Description'!$B$8*'1. Technology Description'!$B$9*T70*86400*1000 -> 405.08331 | V70: =U70*365*K70/1000000 -> 0.048609997 | W70: =ROUNDUP($B$22/V70,0) -> 8142 | X70: =W70*'1. Technology Description'!$B$17/1000 -> 4168.704 | Y70: =1 -> 1 | Z70: =W70*M70+X70*N70+Y70*'2. Cost Inputs'!$D$42+Y70*O70+Y70*'2. Cost Inputs'!$D$44 -> 42091034 | AA70: =Z70*(1+'2. Cost Inputs'!$B$49+'2. Cost Inputs'!$B$50+'2. Cost Inputs'!$B$52)+(W70*M70+X70*N70+Y70*'2. Cost Inputs'!$D$42)*'2. Cost Inputs'!$B$51 -> 68263860 | AB70: =(L70*(1+L70)^'2. Cost Inputs'!$B$6)/((1+L70)^'2. Cost Inputs'!$B$6-1) -> 0.13147378 | AC70: =AA70*AB70 -> 8974907.6 | AD70: ='1. Technology Description'!$B$17*24/1000/(U70/1000000) -> 30334.501 | AE70: =AD70*Q70*$B$22 -> 3601465.4 | AF70: =Y70*6*S70 -> 900000 | AG70: =AA70*P70 -> 4778470.2 | AH70: =R70*'2. Cost Inputs'!$D$25*Y70 -> 1900800 | AI70: =AC70+AE70+AF70+AG70+AH70+(('1. Technology Description'!$B$24/(U70/1000000)/1000)*'1. Technology Description'!$B$26*'2. Cost Inputs'!$D$28*$B$22) -> 20161873 | AJ70: =AI70/$B$22 -> 50945.957
A71: Crew cost | B71: =MIN(AJ55,AJ56) -> 52555.749 | C71: =$AJ$50-MIN(AJ55,AJ56) -> 682.24856 | D71: =MAX(AJ55,AJ56)-$AJ$50 -> 909.66474 | E71: =MAX(AJ55,AJ56) -> 54147.662 | I71: Particle rate worst | J71: ='1. Technology Description'!$B$10 -> 150 | K71: =($B$18+$B$19)*'2. Cost Inputs'!$B$5 -> 0.32876712 | L71: ='2. Cost Inputs'!$B$7 -> 0.1 | M71: ='2. Cost Inputs'!$D$40 -> 100 | N71: ='2. Cost Inputs'!$D$41 -> 1500 | O71: ='2. Cost Inputs'!$D$43 -> 7500000 | P71: ='2. Cost Inputs'!$B$35 -> 0.07 | Q71: ='2. Cost Inputs'!$D$24 -> 0.3 | R71: =('2. Cost Inputs'!$B$25*($B$18+$B$20)*365*'2. Cost Inputs'!$B$5) -> 2112000 | S71: ='2. Cost Inputs'!$D$31 -> 150000 | T71: =PI()/6*(J71*10^-9)^3*2160 -> 3.8170351e-18 | U71: =$B$50*'1. Technology Description'!$B$9*T71*86400*1000 -> 344.32081 | V71: =U71*365*K71/1000000 -> 0.041318497 | W71: =ROUNDUP($B$22/V71,0) -> 9579 | X71: =W71*'1. Technology Description'!$B$17/1000 -> 4904.448 | Y71: =1 -> 1 | Z71: =W71*M71+X71*N71+Y71*'2. Cost Inputs'!$D$42+Y71*O71+Y71*'2. Cost Inputs'!$D$44 -> 45839572 | AA71: =Z71*(1+'2. Cost Inputs'!$B$49+'2. Cost Inputs'!$B$50+'2. Cost Inputs'!$B$52)+(W71*M71+X71*N71+Y71*'2. Cost Inputs'!$D$42)*'2. Cost Inputs'!$B$51 -> 75011230 | AB71: =(L71*(1+L71)^'2. Cost Inputs'!$B$6)/((1+L71)^'2. Cost Inputs'!$B$6-1) -> 0.13147378 | AC71: =AA71*AB71 -> 9862009.7 | AD71: ='1. Technology Description'!$B$17*24/1000/(U71/1000000) -> 35687.648 | AE71: =AD71*Q71*$B$22 -> 4237018.2 | AF71: =Y71*6*S71 -> 900000 | AG71: =AA71*P71 -> 5250786.1 | AH71: =R71*'2. Cost Inputs'!$D$25*Y71 -> 1900800 | AI71: =AC71+AE71+AF71+AG71+AH71+(('1. Technology Description'!$B$24/(U71/1000000)/1000)*'1. Technology Description'!$B$26*'2. Cost Inputs'!$D$28*$B$22) -> 22157943 | AJ71: =AI71/$B$22 -> 55989.72
A72: Vessel fuel/yr | B72: =MIN(AJ53,AJ54) -> 50836.483 | C72: =$AJ$50-MIN(AJ53,AJ54) -> 2401.5149 | D72: =MAX(AJ53,AJ54)-$AJ$50 -> 2401.5149 | E72: =MAX(AJ53,AJ54) -> 55639.512 | I72: Particle rate best | J72: ='1. Technology Description'!$B$10 -> 150 | K72: =($B$18+$B$19)*'2. Cost Inputs'!$B$5 -> 0.32876712 | L72: ='2. Cost Inputs'!$B$7 -> 0.1 | M72: ='2. Cost Inputs'!$D$40 -> 100 | N72: ='2. Cost Inputs'!$D$41 -> 1500 | O72: ='2. Cost Inputs'!$D$43 -> 7500000 | P72: ='2. Cost Inputs'!$B$35 -> 0.07 | Q72: ='2. Cost Inputs'!$D$24 -> 0.3 | R72: =('2. Cost Inputs'!$B$25*($B$18+$B$20)*365*'2. Cost Inputs'!$B$5) -> 2112000 | S72: ='2. Cost Inputs'!$D$31 -> 150000 | T72: =PI()/6*(J72*10^-9)^3*2160 -> 3.8170351e-18 | U72: =$D$50*'1. Technology Description'!$B$9*T72*86400*1000 -> 465.8458 | V72: =U72*365*K72/1000000 -> 0.055901496 | W72: =ROUNDUP($B$22/V72,0) -> 7080 | X72: =W72*'1. Technology Description'!$B$17/1000 -> 3624.96 | Y72: =1 -> 1 | Z72: =W72*M72+X72*N72+Y72*'2. Cost Inputs'!$D$42+Y72*O72+Y72*'2. Cost Inputs'!$D$44 -> 43670440 | AA72: =Z72*(1+'2. Cost Inputs'!$B$49+'2. Cost Inputs'!$B$50+'2. Cost Inputs'!$B$52)+(W72*M72+X72*N72+Y72*'2. Cost Inputs'!$D$42)*'2. Cost Inputs'!$B$51 -> 71106792 | AB72: =(L72*(1+L72)^'2. Cost Inputs'!$B$6)/((1+L72)^'2. Cost Inputs'!$B$6-1) -> 0.13147378 | AC72: =AA72*AB72 -> 9348678.5 | AD72: ='1. Technology Description'!$B$17*24/1000/(U72/1000000) -> 26377.827 | AE72: =AD72*Q72*$B$22 -> 3131709.1 | AF72: =Y72*6*S72 -> 900000 | AG72: =AA72*P72 -> 4977475.4 | AH72: =R72*'2. Cost Inputs'!$D$25*Y72 -> 1900800 | AI72: =AC72+AE72+AF72+AG72+AH72+(('1. Technology Description'!$B$24/(U72/1000000)/1000)*'1. Technology Description'!$B$26*'2. Cost Inputs'!$D$28*$B$22) -> 20264080 | AJ72: =AI72/$B$22 -> 51204.219
A73: Particle output rate | B73: =MIN(AJ71,AJ72) -> 51204.219 | C73: =$AJ$50-MIN(AJ71,AJ72) -> 2033.778 | D73: =MAX(AJ71,AJ72)-$AJ$50 -> 2751.7224 | E73: =MAX(AJ71,AJ72) -> 55989.72 | I73: PPS worst
A74: Power per unit | B74: =MIN(AJ51,AJ52) -> 39890.592 | C74: =$AJ$50-MIN(AJ51,AJ52) -> 13347.405 | D74: =MAX(AJ51,AJ52)-$AJ$50 -> 7415.2252 | E74: =MAX(AJ51,AJ52) -> 60653.223 | I74: PPS best

Sheet 3b. Outputs - Ship Piggyback
A1: Container Ship Piggyback Scenario
A2: Rent deck slots on container ships already running liners. The spray train is sized to its own 4.5 MW of generation (rows 40-43); liner schedules set the spray fraction.
A3: Piggyback Assumptions
B4: Value | C4: Unit | D4: Notes | G4: Sources
A5: Containerized mounting capital per vessel | B5: 100000 | C5: $/vessel | D5: Gear mounting and integration only, no hull purchased | E5: Assumption: gear mounting and integration only, no hull purchased. | G5: Assumption: gear mounting and integration only, no hull purchased.
A6: Technicians per vessel | B6: 3 | C6: people | D6: Ship crew already covered | E6: Assumption: 3 technicians per vessel. | G6: Assumption: 3 technicians per vessel.
A7: Technician annual cost | B7: 180000 | C7: $/person | D7: Loaded annual cost | E7: Assumption (loaded annual cost). | G7: Assumption (loaded annual cost).
A8: Energy price (own generation: tab 2 diesel rate) | B8: ='2. Cost Inputs'!D24 -> 0.3 | C8: $/kWh | D8: The spray train brings its own gensets (tab 2 row 41 capex), so power is priced at the tab-2 diesel rate. Until 10/07 a separate "shipboard" $0.25 was typed here. | E8: Assumption within noted range: grid ~$0.10-0.15, marine diesel generation ~$0.20-0.35/kWh. | G8: Assumption within noted range: grid ~$0.10-0.15, marine diesel generation ~$0.20-0.35/kWh.
A9: Spray-train energy (compression + atomization) | B9: ='2. Cost Inputs'!B24*B8*$B$43 -> 3888000 | C9: $/yr | D9: kWh/tonne x shipboard price x annual production
A10: Deck-slot rental per vessel per year | B10: 2000000 | C10: $/vessel/yr | D10: Assumption | E10: Assumption (deck-slot rental per vessel-year). | G10: Assumption (deck-slot rental per vessel-year).
A11: Seawater skid, containerized (pumps, filtration, UV) | B11: 80000 | C11: $/vessel | D11: Until 10/07 typed inside the row-22 formula.
A12: Mission & Endurance
A13: Spray time - moving (underway) | B13: 0.3652968 | C13: % of avail. time | D13: % of available time spraying; host vessel is underway on its route regardless | G13: Assumption: host vessel underway on its route regardless.
A14: Spray time - on station | B14: 0 | C14: % of avail. time | D14: Zero: host vessel does not hold station to spray | G14: Structural zero: host vessel does not hold station to spray.
A15: Transit time (no spray) | B15: 0 | C15: % of avail. time | D15: Zero: no dedicated transit legs - host vessel is on its route | G15: Structural zero: no dedicated transit legs.
A16: Operating days per year | B16: =(B13+B14+B15)*365*'2. Cost Inputs'!$B$5 -> 120 | C16: days | D16: = (spray + transit) % of available time x 365 x equipment availability
A17: Fuel & endurance | D17: Host vessel carries fuel; deck-slot rental covers logistics; no tank endurance limit
A19: Recomputed Levelized Cost
B20: $/yr | C20: $/tonne of aerosol | D20: Notes
A21: Nozzles & compression capex | B21: =B42*'2. Cost Inputs'!D40+B42*'1. Technology Description'!B17/1000*'2. Cost Inputs'!D41 -> 7628906.2
A22: Seawater skid + mounting | B22: =B5+B11 -> 180000 | C22: Skid + container mounting, no hull (single vessel)
A23: Total purchased equipment | B23: =B21+B22 -> 7808906.2
A24: Total capex (x1.8 contingency) | B24: =B23*(1+'2. Cost Inputs'!B49+'2. Cost Inputs'!B50+'2. Cost Inputs'!B51+'2. Cost Inputs'!B52) -> 14056031
A25: Capital recovery factor | B25: =('2. Cost Inputs'!B7*(1+'2. Cost Inputs'!B7)^'2. Cost Inputs'!B6)/((1+'2. Cost Inputs'!B7)^'2. Cost Inputs'!B6-1) -> 0.13147378
A26: Annualized capital | B26: =B24*B25 -> 1847999.5 | C26: =B26/$B$43 -> 4325.474
A27: Energy | B27: =B9 -> 3888000 | C27: =B27/$B$43 -> 9100.3504 | D27: Spray-train energy at the shipboard price (B9). Until 10/07 this row priced energy again at the tab-2 diesel rate and the total added B9 on top, counting energy twice.
A28: Technician (replaces crew) | B28: =B6*B7 -> 540000 | C28: =B28/$B$43 -> 1263.9375
A29: Deck-slot rental | B29: =B10 -> 2000000 | C29: =B29/$B$43 -> 4681.2502
A30: Maintenance & insurance | B30: =B24*'2. Cost Inputs'!B35 -> 983922.19 | C30: =B30/$B$43 -> 2302.993
A31: Total Annual Cost | B31: =(B26+B27+B28+B29+B30) -> 9259921.7
A32: Levelized Cost per Tonne | C32: =B31/$B$43 -> 21674.005
A34: Container Ship vs Dedicated Vessel
B35: Value | C35: Unit | D35: Notes
A36: Dedicated vessel: $/tonne of aerosol | B36: ='3a. Outputs - Dedicated Vessel'!G5 -> 54047.979 | C36: From main model
A37: Container ship: $/tonne of aerosol | B37: =C32 -> 21674.005
A38: Cost relative to dedicated vessel | B38: =B37/B36 -> 0.40101417
A40: Host-ship sizing (own generation)
A41: Power per host ship, own gensets | B41: 4500 | C41: kW | D41: 4.5 MW of containerized gensets is 3 to 5 forty-foot boxes; with compressors the train takes ~20-30 TEU of slots. Sizes the train on this tab. Until 10/07 the train was tab 2's 10^16/s unit (4.2 MW) while 6c assumed 2 MW from the host.
A42: Nozzles per host ship | B42: =B41*1000/'1. Technology Description'!B17 -> 8789.0625 | C42: nozzles | D42: Power per ship / watts per nozzle (tab 1 B17).
A43: Production per host ship | B43: =($B$13+$B$14)*$B$42*'2. Cost Inputs'!$B$11 -> 427.2363 | C43: tonnes/yr | D43: Spray fraction x nozzles x aerosol per nozzle-year (tab 2 B11). Read by 6c.

Sheet 3c. Outputs - Fixed Platform
A1: Fixed Coastal Platform Scenario
A2: Fixed platforms: stay put, run continuously, shore or renewable power, no propulsion fuel. Cable to shore not priced: beyond a few km it can rival platform capex (~$0.8-1.5M/km HVAC export, install +30-60%, 2025-26 market data).
A3: Platform Assumptions
B4: Value | C4: Unit | D4: Notes | G4: Sources
A5: Platform capital per unit | B5: 3000000 | C5: $/platform | D5: Moored buoy / small jack-up / repurposed barge with mooring. Assumption: purpose-built marine structure, far above a $50k container slot. | G5: Assumption: moored buoy / small jack-up / repurposed barge with mooring.
A6: Technicians per platform | B6: 1 | C6: people | D6: Largely automated; periodic maintenance from shore. Closer to the piggyback technician model than a 6-person crew. | G6: Assumption: largely automated, periodic maintenance from shore.
A7: Technician annual cost | B7: 180000 | C7: $/person | D7: Loaded annual cost incl. boat transfers for maintenance trips. | E7: Assumption (includes boat transfers for maintenance trips).
A8: Shore power price | B8: 0.15 | C8: $/kWh | D8: Shore power, cheaper than marine diesel ($0.30/kWh). Set to 0.30 to model diesel gensets. | G8: Assumption: shore-power price; set to 0.30 to model diesel gensets.
A9: Siting + permitting per platform | B9: 250000 | C9: $/platform | D9: New: environmental review, marine permits, consultation near a populated coast. Amortized as capital. | G9: Assumption: environmental review, marine permits, consultation near a populated coast.
A10: Mooring + station-keeping O&M | B10: 60000 | C10: $/platform/yr | D10: New annual cost: mooring inspection, anti-fouling, station-keeping for a fixed marine structure. | E10: Assumption: mooring inspection, anti-fouling, station-keeping O&M.
A12: Mission & Endurance
A13: Spray time - moving (underway) | B13: 0 | C13: % of avail. time | D13: Zero: fixed platform does not move | G13: Structural zero: fixed platform does not move.
A14: Spray time - on station | B14: 0.3652968 | C14: % of avail. time | D14: % of available time spraying; platform is permanently on station | G14: Assumption: platform permanently on station.
A15: Transit time (no spray) | B15: 0 | C15: % of avail. time | D15: Zero: fixed platform has no transit | G15: Structural zero: no transit legs.
A16: Operating days per year | B16: =(B13+B14+B15)*365*'2. Cost Inputs'!$B$5 -> 120 | C16: days | D16: = (spray + transit) % of available time x 365 x equipment availability
A17: Fuel & endurance | D17: Shore-powered; no fuel endurance limit; crew access in suitable weather windows
A19: Recomputed Levelized Cost
B20: $/yr | C20: $/tonne of aerosol | D20: Notes
A21: Nozzles & compression capex | B21: ='2. Cost Inputs'!B13*'2. Cost Inputs'!D40+'2. Cost Inputs'!B14*'2. Cost Inputs'!D41 -> 7066677.5
A22: Seawater skid | B22: ='2. Cost Inputs'!D42 -> 25000 | C22: Intake/filtration/UV skid, one per platform-edge (single platform)
A23: Platform structure + siting | B23: =B5+B9 -> 3250000 | C23: Fixed offshore structure + permitting, single platform
A24: Total purchased equipment | B24: =B21+B22+B23 -> 10341678
A25: Total capex (contingency stack) | B25: =B24*(1+'2. Cost Inputs'!B49+'2. Cost Inputs'!B50+'2. Cost Inputs'!B51+'2. Cost Inputs'!B52) -> 18615020
A26: Capital recovery factor | B26: =('2. Cost Inputs'!B7*(1+'2. Cost Inputs'!B7)^'2. Cost Inputs'!B6)/((1+'2. Cost Inputs'!B7)^'2. Cost Inputs'!B6-1) -> 0.13147378
A27: Annualized capital | B27: =B25*B26 -> 2447386.9 | C27: =B27/(($B$13+$B$14)*'2. Cost Inputs'!$B$15) -> 6184.1711
A28: Energy (shore power) | B28: ='2. Cost Inputs'!B24*B8*(($B$13+$B$14)*'2. Cost Inputs'!$B$15) -> 1800732.7 | C28: =B28/(($B$13+$B$14)*'2. Cost Inputs'!$B$15) -> 4550.1752 | D28: Same kWh/tonne as main model, priced at shore power. No propulsion fuel: platform does not move.
A29: Technician (replaces crew) | B29: =B6*B7 -> 180000 | C29: =B29/(($B$13+$B$14)*'2. Cost Inputs'!$B$15) -> 454.83237 | D29: Automated platform, minimal staffing
A30: Mooring + station-keeping O&M | B30: =B10 -> 60000 | C30: =B30/(($B$13+$B$14)*'2. Cost Inputs'!$B$15) -> 151.61079
A31: Maintenance & insurance | B31: =B25*'2. Cost Inputs'!B35 -> 1303051.4 | C31: =B31/(($B$13+$B$14)*'2. Cost Inputs'!$B$15) -> 3292.6108 | D31: Same 7% of capex as main model
A32: Total Annual Cost | B32: =B27+B28+B29+B30+B31 -> 5791171
A33: Levelized Cost per Tonne | C33: =B32/(($B$13+$B$14)*'2. Cost Inputs'!$B$15) -> 14633.4
A35: Fixed Platform vs Other Sitings
B36: Value | C36: Unit | D36: Notes
A37: Dedicated vessel: $/tonne of aerosol | B37: ='3a. Outputs - Dedicated Vessel'!G5 -> 54047.979
A38: Container ship: $/tonne of aerosol | B38: ='3b. Outputs - Ship Piggyback'!C32 -> 21674.005
A39: Fixed platform: $/tonne of aerosol | B39: =C33 -> 14633.4
A40: Cost relative to dedicated vessel | B40: =B39/B37 -> 0.27074833

Sheet 3d. Outputs - Stationary Vessel
A1: Stationary Vessel Scenario
A2: Transit to position, then hold station. Fuel = hotel burn all days + propulsion on transit days.
A3: Mission & Endurance | G3: Sources
A4: Spray time - moving (underway) | B4: 0 | C4: % of avail. time | D4: Zero: this vessel does not spray while underway | G4: Structural zero: does not spray while underway.
A5: Spray time - on station | B5: 0.3652968 | C5: % of avail. time | D5: Spraying while holding station | G5: Assumption: sprays while holding station.
A6: Transit time (no spray) | B6: 0.01217656 | C6: % of avail. time | D6: Steam out and back; one round trip per year | G6: Assumption: steam out and back, one round trip per year.
A7: Operating days per year | B7: =(B4+B5+B6)*365*'2. Cost Inputs'!$B$5 -> 124 | C7: days | D7: = (spray + transit) % of available time x 365 x equipment availability
A8: Effective production | B8: =(B4+B5)*'2. Cost Inputs'!$B$15 -> 395.7502 | C8: tonnes/yr | D8: = spray % x equipment-basis annual production (availability already applied)
A9: Endurance per tank (on station) | B9: ='3a. Outputs - Dedicated Vessel'!$B$26*'2. Cost Inputs'!B27/'2. Cost Inputs'!B26 -> 333.33333 | C9: days | D9: 90% of tank at hotel burn only - about 11 months on station
A10: Missions per year (tank-limited) | B10: =ROUNDUP(B7/B9,0) -> 1 | C10: missions | D10: Returns to port to refuel this many times
A11: Hotel fuel per year | B11: =B7*'2. Cost Inputs'!B26 -> 334800 | C11: L/yr | D11: = operating days x hotel burn
A12: Transit fuel per year | B12: =(B4+B6)*365*'2. Cost Inputs'!$B$5*'2. Cost Inputs'!B25 -> 64000 | C12: L/yr | D12: = (spray-moving + transit) % x 365 x availability x underway burn
A15: Recomputed Levelized Cost
B16: $/yr | C16: $/tonne of aerosol | D16: Notes
A17: Capital recovery factor | B17: =('2. Cost Inputs'!B7*(1+'2. Cost Inputs'!B7)^'2. Cost Inputs'!B6)/((1+'2. Cost Inputs'!B7)^'2. Cost Inputs'!B6-1) -> 0.13147378
A18: Annualized capital | B18: ='2. Cost Inputs'!B53*B17 -> 9566691.9 | C18: =B18/$B$8 -> 24173.562
A19: Energy (spray) | B19: ='2. Cost Inputs'!B24*'2. Cost Inputs'!D24*$B$8 -> 3601465.4 | C19: =B19/$B$8 -> 9100.3504
A20: Seawater pumping + filtration | B20: ='2. Cost Inputs'!B28*'2. Cost Inputs'!D28*$B$8 -> 6229.4098 | C20: =B20/$B$8 -> 15.740762
A21: Seawater feedstock | B21: ='2. Cost Inputs'!B20*'2. Cost Inputs'!D20*$B$8 -> 0 | C21: =B21/$B$8 -> 0
A22: Crew | B22: ='2. Cost Inputs'!B31*'2. Cost Inputs'!D31 -> 900000 | C22: =B22/$B$8 -> 2274.1619
A23: Maintenance & insurance | B23: ='2. Cost Inputs'!B53*'2. Cost Inputs'!B35 -> 5093551.4 | C23: =B23/$B$8 -> 12870.622
A24: Vessel energy (hotel + transit) | B24: =(B11+B12)*'2. Cost Inputs'!D26 -> 358920 | C24: =B24/$B$8 -> 906.93575 | D24: (operating days x hotel burn + moving days x underway burn) x diesel price
A25: Total Annual Cost | B25: =SUM(B18:B24) -> 19526858
A26: Levelized Cost per Tonne | C26: =B25/$B$8 -> 49341.373
A28: Stationary vs Moving Vessel
B29: Value | C29: Unit | D29: Notes
A30: Moving vessel: $/tonne of aerosol (tab 3a) | B30: ='3a. Outputs - Dedicated Vessel'!G5 -> 54047.979 | C30: From main model
A31: Stationary vessel: $/tonne of aerosol | B31: =C26 -> 49341.373
A32: Saving vs moving vessel | B32: =B30-B31 -> 4706.6054 | C32: $/tonne
A33: Cost relative to moving vessel | B33: =B31/B30 -> 0.91291801

Sheet 4. Scenario Comparison
A1: 4. Scenario Comparison
A2: All values pulled live from tabs 3a-3d (green fill); nothing is computed here. Sources for each number sit on its home tab.
A4: Levelized cost per tonne of aerosol
A5: Scenario | B5: $/tonne | C5: $/yr | D5: vs dedicated (3a) | E5: Note
A6: 3a. Dedicated vessel | B6: ='3a. Outputs - Dedicated Vessel'!G5 -> 54047.979 | C6: ='3a. Outputs - Dedicated Vessel'!B13 -> 21389498 | D6: anchor | E6: Main model.
A7: 3b. Ship piggyback | B7: ='3b. Outputs - Ship Piggyback'!C32 -> 21674.005 | C7: ='3b. Outputs - Ship Piggyback'!B31 -> 9259921.7 | D7: ='3b. Outputs - Ship Piggyback'!B38 -> 0.40101417 | E7: Rent deck slots; host vessel runs its route.
A8: 3c. Fixed platform | B8: ='3c. Outputs - Fixed Platform'!C33 -> 14633.4 | C8: ='3c. Outputs - Fixed Platform'!B32 -> 5791171 | D8: ='3c. Outputs - Fixed Platform'!B40 -> 0.27074833 | E8: Moored buoy / jack-up; shore power.
A9: 3d. Stationary vessel | B9: ='3d. Outputs - Stationary Vessel'!C26 -> 49341.373 | C9: ='3d. Outputs - Stationary Vessel'!B25 -> 19526858 | D9: ='3d. Outputs - Stationary Vessel'!B33 -> 0.91291801 | E9: Steam out and back once; holds station.

Sheet 5a. Cooling Model - Local
A1: Cost of Cooling: Cost per Unit of Cooling Produced
A2: Converts cost per tonne of aerosol (from the TEA) into cost per unit of cooling, using the particle-size physics below.
A4: Aerosol Delivery | H4: Sources
A5: Survival factor | B5: 0.3 | C5: fraction | D5: Fraction surviving in-plume coagulation/deposition to cloud base. Open research gap (2025 plume review; CS-06 targets it). Range 0.1-0.5. | H5: Hernandez-Jaramillo et al. 2025a, Front. Mar. Sci. 12:1450175, p.1: effectiveness "depends on what fraction of the sea salt aerosols are incorporated into clouds after being emitted"; still an open research gap, so 0.3 is a scenario choice.
A6: Boundary-layer mixing depth | B6: 900 | C6: m | D6: Measured: plumes reached cloud base at 825-900 m across five GBR campaigns (CS-06 Final Report 2025). | H6: CS-06 Final Report 2025, p.2: "plumes consistently reached cloud base heights (800 - 900 metres) under typical trade-wind and low-wind speed doldrum type atmospheric conditions." ERL 2025 abstract: plume detected "just below cloud bases at 700-900 m altitudes".
A7: Cloud susceptibility
A8: Particles per tonne of salt | B8: ='1. Technology Description'!B11 -> 2.6198345e+20 | C8: #/tonne | D8: From tab 1
A9: Background cloud droplet number | B9: 100 | C9: /cm3 | D9: Natural marine background. CS-06 2025 p.34: GBR runs 50-200/cm3, most common ~100. | H9: CS-06 Final Report 2025, pp.25-26: "background CCN concentrations range from approximately 50 to 200 cm-3... The most common value is near 100 cm-3".
A10: Required droplet addition | B10: =(B18-1)*B9 -> 30 | C10: /cm3 | D10: Spray up to the measured ceiling: 200 total - 100 background = add 100/cm3. Ceiling measured, CS-06 p.34.
A11: Area per tonne | B11: =B8*B5/(B10*1000000*B6*1000000) -> 2910.9272 | C11: km2/tonne | D11: Particles available / needed per km2. Not applied as a factor: ~9 in 100 windowed arrivals don't activate at 0.5% SS (field-measured, ERL 2025); worse at 0.2% SS.
A12: Critical activation diameter (Köhler threshold) | B12: 50 | C12: nm | D12: Hernandez-Jaramillo 2025 (ERL): ~50 nm activates at 0.5% SS over the GBR; ~73 nm at 0.2% SS (trade-cumulus Hoppel minimum). | H12: ERL 2025, p.9: "a critical diameter of ~ 50 nm at 0.5% supersaturation (SS) and ~73 nm at 0.2% SS" (GBR seawater).
A13: Unused - do not wire (superseded by cloud availability) | B13: 0.43 | C13: fraction | D13: Neutralized 2026-09-09: overlaps cloud availability, same weather gate, would double-count. No formulas reference this input.
A14: Cloud Radiative Effect
B15: Value | C15: Unit | D15: Notes | H15: Sources
A16: Cloud-top shortwave (daytime) | B16: 475 | C16: W/m2 | D16: Downwelling SW at cloud top, daytime marine. 24h-mean is lower; this is the active-cooling value. | H16: Assumption (daytime marine cloud-top shortwave)
A17: Marine cloud albedo | B17: 0.4 | C17: - | D17: Stratocumulus deck albedo, ~0.5. | H17: Assumption: literature-typical stratocumulus albedo. Talked with Graham who suggested 0.30 a lower range.
A18: Droplet-number enhancement | B18: 1.3 | C18: x | D18: Droplet-number enhancement vs background, capped at the measured ~200/cm3 ceiling (CS-06 p.34) = 200/background = 2.0x here.
A19: Local forcing under brightened cloud | B19: =B16*B17*(1-B17)*(1/3)*LN(B18) -> 9.969842 | C19: W/m2 | D19: Twomey: Fsw x Ac x (1-Ac) x (1/3) x ln(Nd ratio)
A20: Daytime averaging | B20: 0.4 | D20: Daytime averaging ~0.4: brightening only reflects sun by day, so 24-h forcing is ~0.3-0.5 of peak. | H20: Assumption (daytime-averaging factor ~0.4).
A21: Cloud availability | B21: 0.2 | D21: CS-01 Final Report 2025, p.11: susceptible low cloud in summer '20% at the north and increases to 55% at the south'. | H21: CS-01 Final Report 2025, p.11: occurrence of susceptible low cloud in summer "is 20% at the north and increases to 55% at the south"
A22: Realization Factor | B22: =B21*B20 -> 0.08 | D22: Daytime averaging x cloud availability
A23: Surface energy budget sensitivity
A24: Aerosol lifetime | B24: 3 | C24: days | D24: Boundary-layer residence (uncertain) | H24: Assumption (boundary-layer residence; uncertain).
A25: Local temperature sensitivity | B25: 0.0225 | C25: degC/(W/m2) | D25: Local forcing to local surface cooling. Harrison et al. 2019, RRAP T14 report. | H25: Harrison et al. 2019 (T14), pp.32-33: relationship "approximately linear... with the gradient of 0.225°C per 10 Wm-2 reduction in solar forcing"
A27: From the Aerosol TEA
B28: Value | C28: Unit | D28: Source
A29: Levelized cost of aerosol | B29: ='3a. Outputs - Dedicated Vessel'!G5 -> 54047.979 | C29: $/tonne of aerosol | D29: Headline from the TEA Outputs tab
A31: Cooling Conversion
B32: Value | C32: Unit | D32: Notes / Source
A33: Cooling produced per tonne of aerosol | B33: =(B19*B25*(B11*100)*B24)*B20*B21 -> 15671.601 | C33: degC-ha-days/tonne | D33: local forcing x local temperature sensitivity x area (ha) x lifetime (days) x realization
A34: Cost of cooling produced | B34: =B29/B33 -> 3.4487847 | C34: $/degC-ha-day | D34: Aerosol cost / cooling per tonne

Sheet 5b. Cooling-Value Sensitivity
A1: Cooling-Value Sensitivity: Cost per Unit of Cooling
A2: One-way sensitivity of cost per degC-ha-day to model and cost drivers.
A3: Sensitivity: what Moves the Cost per Unit Cooling
A4: One-way sensitivity of cost per degC-ha-day. Model drivers scale cooling directly (the 3a tornado can't see them); cost drivers pull live from 3a. Survival is the dominant, softest bar. Particle size fixed at 150 nm.
A5: Driver | B5: Downside input | C5: Base | D5: Upside input | E5: at downside ($) | F5: at base ($) | G5: at upside ($) | H5: Swing ($) | I5: Sources | J5: spacer (hidden) | K5: cost-reducing span | L5: cost-raising span | M5: max (label helper) | N5: tail (hidden)
A6: Model: Marine cloud albedo | B6: 0.3 | C6: ='5a. Cooling Model - Local'!$B$17 -> 0.4 | D6: 0.6 | E6: ='5a. Cooling Model - Local'!$B$34*(('5a. Cooling Model - Local'!$B$17*(1-'5a. Cooling Model - Local'!$B$17))/(B6*(1-B6))) -> 3.9414682 | F6: ='5a. Cooling Model - Local'!$B$34 -> 3.4487847 | G6: ='5a. Cooling Model - Local'!$B$34*(('5a. Cooling Model - Local'!$B$17*(1-'5a. Cooling Model - Local'!$B$17))/(D6*(1-D6))) -> 3.4487847 | H6: =MAX(E6,F6,G6)-MIN(E6,F6,G6) -> 0.49268352 | I6: Sensitivity bounds around the tab 5a base cloud albedo; see tab 5a Sources. | J6: =MIN(E6,F6,G6) -> 3.4487847 | K6: =MAX(0,F6-MIN(E6,G6)) -> 0 | L6: =MAX(0,MAX(E6,G6)-F6) -> 0.49268352 | M6: =J6+K6+L6 -> 3.9414682 | N6: =20-MAX(E6:G6) -> 16.058532
A7: Cost: Energy price | B7: ='3a. Outputs - Dedicated Vessel'!B58 -> 0.45 | C7: ='2. Cost Inputs'!D24 -> 0.3 | D7: ='3a. Outputs - Dedicated Vessel'!D58 -> 0.18 | E7: =MAX('3a. Outputs - Dedicated Vessel'!AJ67,'3a. Outputs - Dedicated Vessel'!AJ68)/'5a. Cooling Model - Local'!$B$33 -> 3.6874453 | F7: ='5a. Cooling Model - Local'!$B$34 -> 3.4487847 | G7: =MIN('3a. Outputs - Dedicated Vessel'!AJ67,'3a. Outputs - Dedicated Vessel'!AJ68)/'5a. Cooling Model - Local'!$B$33 -> 3.1648238 | H7: =MAX(E7,F7,G7)-MIN(E7,F7,G7) -> 0.52262147 | J7: =MIN(E7,F7,G7) -> 3.1648238 | K7: =MAX(0,F7-MIN(E7,G7)) -> 0.28396085 | L7: =MAX(0,MAX(E7,G7)-F7) -> 0.23866061 | M7: =J7+K7+L7 -> 3.6874453 | N7: =20-MAX(E7:G7) -> 16.312555
A8: Cost: Vessel cost | B8: ='3a. Outputs - Dedicated Vessel'!B55 -> 56250000 | C8: ='2. Cost Inputs'!D43 -> 7500000 | D8: ='3a. Outputs - Dedicated Vessel'!D55 -> 22500000 | E8: =MAX('3a. Outputs - Dedicated Vessel'!AJ61,'3a. Outputs - Dedicated Vessel'!AJ62)/'5a. Cooling Model - Local'!$B$33 -> 4.3716526 | F8: ='5a. Cooling Model - Local'!$B$34 -> 3.4487847 | G8: =MIN('3a. Outputs - Dedicated Vessel'!AJ61,'3a. Outputs - Dedicated Vessel'!AJ62)/'5a. Cooling Model - Local'!$B$33 -> 2.617458 | H8: =MAX(E8,F8,G8)-MIN(E8,F8,G8) -> 1.7541946 | J8: =MIN(E8,F8,G8) -> 2.617458 | K8: =MAX(0,F8-MIN(E8,G8)) -> 0.83132669 | L8: =MAX(0,MAX(E8,G8)-F8) -> 0.92286791 | M8: =J8+K8+L8 -> 4.3716526 | N8: =20-MAX(E8:G8) -> 15.628347
A9: Cost: Nozzle unit cost | B9: ='3a. Outputs - Dedicated Vessel'!B54 -> 1000 | C9: ='2. Cost Inputs'!D40 -> 100 | D9: ='3a. Outputs - Dedicated Vessel'!D54 -> 10 | E9: =MAX('3a. Outputs - Dedicated Vessel'!AJ59,'3a. Outputs - Dedicated Vessel'!AJ60)/'5a. Cooling Model - Local'!$B$33 -> 3.8255796 | F9: ='5a. Cooling Model - Local'!$B$34 -> 3.4487847 | G9: =MIN('3a. Outputs - Dedicated Vessel'!AJ59,'3a. Outputs - Dedicated Vessel'!AJ60)/'5a. Cooling Model - Local'!$B$33 -> 3.3542521 | H9: =MAX(E9,F9,G9)-MIN(E9,F9,G9) -> 0.47132753 | J9: =MIN(E9,F9,G9) -> 3.3542521 | K9: =MAX(0,F9-MIN(E9,G9)) -> 0.094532604 | L9: =MAX(0,MAX(E9,G9)-F9) -> 0.37679493 | M9: =J9+K9+L9 -> 3.8255796 | N9: =20-MAX(E9:G9) -> 16.17442
A10: Cost: Annual utilization | B10: ='3a. Outputs - Dedicated Vessel'!B53 -> 0.19726027 | C10: =('3a. Outputs - Dedicated Vessel'!$B$18+'3a. Outputs - Dedicated Vessel'!$B$19)*'2. Cost Inputs'!$B$5 -> 0.32876712 | D10: ='3a. Outputs - Dedicated Vessel'!D53 -> 0.42739726 | E10: =MAX('3a. Outputs - Dedicated Vessel'!AJ57,'3a. Outputs - Dedicated Vessel'!AJ58)/'5a. Cooling Model - Local'!$B$33 -> 3.6725458 | F10: ='5a. Cooling Model - Local'!$B$34 -> 3.4487847 | G10: =MIN('3a. Outputs - Dedicated Vessel'!AJ57,'3a. Outputs - Dedicated Vessel'!AJ58)/'5a. Cooling Model - Local'!$B$33 -> 3.3017319 | H10: =MAX(E10,F10,G10)-MIN(E10,F10,G10) -> 0.37081382 | J10: =MIN(E10,F10,G10) -> 3.3017319 | K10: =MAX(0,F10-MIN(E10,G10)) -> 0.14705272 | L10: =MAX(0,MAX(E10,G10)-F10) -> 0.22376109 | M10: =J10+K10+L10 -> 3.6725458 | N10: =20-MAX(E10:G10) -> 16.327454
A11: Cost: Crew cost | B11: ='3a. Outputs - Dedicated Vessel'!B52 -> 210000 | C11: ='2. Cost Inputs'!D31 -> 150000 | D11: ='3a. Outputs - Dedicated Vessel'!D52 -> 105000 | E11: =MAX('3a. Outputs - Dedicated Vessel'!AJ55,'3a. Outputs - Dedicated Vessel'!AJ56)/'5a. Cooling Model - Local'!$B$33 -> 3.4551454 | F11: ='5a. Cooling Model - Local'!$B$34 -> 3.4487847 | G11: =MIN('3a. Outputs - Dedicated Vessel'!AJ55,'3a. Outputs - Dedicated Vessel'!AJ56)/'5a. Cooling Model - Local'!$B$33 -> 3.3535659 | H11: =MAX(E11,F11,G11)-MIN(E11,F11,G11) -> 0.10157949 | J11: =MIN(E11,F11,G11) -> 3.3535659 | K11: =MAX(0,F11-MIN(E11,G11)) -> 0.095218714 | L11: =MAX(0,MAX(E11,G11)-F11) -> 0.0063607766 | M11: =J11+K11+L11 -> 3.4551454 | N11: =20-MAX(E11:G11) -> 16.544855
A12: Model: Cloud-top shortwave | B12: 400 | C12: ='5a. Cooling Model - Local'!$B$16 -> 475 | D12: 550 | E12: ='5a. Cooling Model - Local'!$B$34*('5a. Cooling Model - Local'!$B$16/B12) -> 4.0954318 | F12: ='5a. Cooling Model - Local'!$B$34 -> 3.4487847 | G12: ='5a. Cooling Model - Local'!$B$34*('5a. Cooling Model - Local'!$B$16/D12) -> 2.9784958 | H12: =MAX(E12,F12,G12)-MIN(E12,F12,G12) -> 1.1169359 | I12: Sensitivity bounds around the tab 5a base cloud-top shortwave; see tab 5a Sources. | J12: =MIN(E12,F12,G12) -> 2.9784958 | K12: =MAX(0,F12-MIN(E12,G12)) -> 0.47028882 | L12: =MAX(0,MAX(E12,G12)-F12) -> 0.64664712 | M12: =J12+K12+L12 -> 4.0954318 | N12: =20-MAX(E12:G12) -> 15.904568
A13: Model: Droplet-number enhancement | B13: 2 | C13: ='5a. Cooling Model - Local'!$B$18 -> 1.3 | D13: 4 | E13: ='5a. Cooling Model - Local'!$B$34*(LN('5a. Cooling Model - Local'!$B$18)/LN(B13)) -> 1.3054051 | F13: ='5a. Cooling Model - Local'!$B$34 -> 3.4487847 | G13: ='5a. Cooling Model - Local'!$B$34*(LN('5a. Cooling Model - Local'!$B$18)/LN(D13)) -> 0.65270254 | H13: =MAX(E13,F13,G13)-MIN(E13,F13,G13) -> 2.7960821 | J13: =MIN(E13,F13,G13) -> 0.65270254 | K13: =MAX(0,F13-MIN(E13,G13)) -> 2.7960821 | L13: =MAX(0,MAX(E13,G13)-F13) -> 0 | M13: =J13+K13+L13 -> 3.4487847 | N13: =20-MAX(E13:G13) -> 16.551215
A14: Model: Aerosol lifetime | B14: 2 | C14: ='5a. Cooling Model - Local'!$B$24 -> 3 | D14: 4 | E14: ='5a. Cooling Model - Local'!$B$34*('5a. Cooling Model - Local'!$B$24/B14) -> 5.173177 | F14: ='5a. Cooling Model - Local'!$B$34 -> 3.4487847 | G14: ='5a. Cooling Model - Local'!$B$34*('5a. Cooling Model - Local'!$B$24/D14) -> 2.5865885 | H14: =MAX(E14,F14,G14)-MIN(E14,F14,G14) -> 2.5865885 | J14: =MIN(E14,F14,G14) -> 2.5865885 | K14: =MAX(0,F14-MIN(E14,G14)) -> 0.86219617 | L14: =MAX(0,MAX(E14,G14)-F14) -> 1.7243923 | M14: =J14+K14+L14 -> 5.173177 | N14: =20-MAX(E14:G14) -> 14.826823
A15: Model: Temperature sensitivity | B15: 0.015 | C15: ='5a. Cooling Model - Local'!$B$25 -> 0.0225 | D15: 0.032 | E15: ='5a. Cooling Model - Local'!$B$34*('5a. Cooling Model - Local'!$B$25/B15) -> 5.173177 | F15: ='5a. Cooling Model - Local'!$B$34 -> 3.4487847 | G15: ='5a. Cooling Model - Local'!$B$34*('5a. Cooling Model - Local'!$B$25/D15) -> 2.4249267 | H15: =MAX(E15,F15,G15)-MIN(E15,F15,G15) -> 2.7482503 | J15: =MIN(E15,F15,G15) -> 2.4249267 | K15: =MAX(0,F15-MIN(E15,G15)) -> 1.0238579 | L15: =MAX(0,MAX(E15,G15)-F15) -> 1.7243923 | M15: =J15+K15+L15 -> 5.173177 | N15: =20-MAX(E15:G15) -> 14.826823
A16: Model: Cooling realization factor | B16: =0.5*C16 -> 0.04 | C16: ='5a. Cooling Model - Local'!$B$22 -> 0.08 | D16: =2*C16 -> 0.16 | E16: ='5a. Cooling Model - Local'!$B$34*('5a. Cooling Model - Local'!$B$22/B16) -> 6.8975693 | F16: ='5a. Cooling Model - Local'!$B$34 -> 3.4487847 | G16: ='5a. Cooling Model - Local'!$B$34*('5a. Cooling Model - Local'!$B$22/D16) -> 1.7243923 | H16: =MAX(E16,F16,G16)-MIN(E16,F16,G16) -> 5.173177 | J16: =MIN(E16,F16,G16) -> 1.7243923 | K16: =MAX(0,F16-MIN(E16,G16)) -> 1.7243923 | L16: =MAX(0,MAX(E16,G16)-F16) -> 3.4487847 | M16: =J16+K16+L16 -> 6.8975693 | N16: =20-MAX(E16:G16) -> 13.102431
A17: Model: Survival factor | B17: 0.1 | C17: ='5a. Cooling Model - Local'!$B$5 -> 0.3 | D17: 0.5 | E17: ='5a. Cooling Model - Local'!$B$34*('5a. Cooling Model - Local'!$B$5/B17) -> 10.346354 | F17: ='5a. Cooling Model - Local'!$B$34 -> 3.4487847 | G17: ='5a. Cooling Model - Local'!$B$34*('5a. Cooling Model - Local'!$B$5/D17) -> 2.0692708 | H17: =MAX(E17,F17,G17)-MIN(E17,F17,G17) -> 8.2770832 | J17: =MIN(E17,F17,G17) -> 2.0692708 | K17: =MAX(0,F17-MIN(E17,G17)) -> 1.3795139 | L17: =MAX(0,MAX(E17,G17)-F17) -> 6.8975693 | M17: =J17+K17+L17 -> 10.346354 | N17: =20-MAX(E17:G17) -> 9.653646
A18: Model: W/m2 brightening | B18: =C18*0.5 -> 4.984921 | C18: ='5a. Cooling Model - Local'!B19 -> 9.969842 | D18: =C18*2 -> 19.939684

Sheet 5c. Benefit - Local - Reef
A1: Local Benefits: Reef-Wide Brightening (Reef Cooling)
A2: Reef-wide deployment on a chartered seasonal fleet: pay only for the bleaching season. Same-day cooling credit only, no persistence or fleet-mobility bonus. Harrison 2019 below as optimistic gut check.
A3: Local on-target delivery factor | B3: 0.5 | C3: fraction | D3: Fraction of sprayed cooling reaching target reef waters (rest drifts off). Same factor on tab 5d. | G3: Assumption (same factor as 5d).
A4: Our Calculation - Deployment and Cost (Chartered Fleet)
A5: Input | B5: Value | C5: Unit | D5: Source / basis | G5: Sources
A6: Reef area cooled | B6: 30000 | C6: km2 | D6: GBR shallow-reef area, ~3 million ha. Reef-wide domain per Harrison et al. 2019. | G6: Harrison et al. 2019 (T14) reef-wide domain; GBR shallow-reef area ~3 million ha.
A7: Marine heatwave duration | B7: 151 | C7: days | D7: ≈ Harrison's Dec 1 - Apr 30 stress window (151 days ≈ 21.6 weeks). Matches the Zhao tab. Replaces the made-up 12 weeks. | G7: Harrison et al. 2019 (T14), p.39: forcing "accumulated over the entire summer from 1 December to 30 April" (151 days = 21.6 weeks).
A8: Peak per-cloud shortwave reduction | B8: ='5a. Cooling Model - Local'!B19/'5a. Cooling Model - Local'!B16 -> 0.020989141 | C8: fraction | D8: Tab-5a nozzle physics. Per-cloud peak exceeds the reef-wide average under either accounting.
A9: Event-average forcing, our accounting | B9: ='5a. Cooling Model - Local'!B19*'5a. Cooling Model - Local'!B22 -> 0.79758736 | C9: W/m2 | D9: Tab-5a peak x realization factor (daylight x seedable-cloud availability). Same-day credit only.
A10: Bleaching-stress relief implied | B10: =B26*(B9/B35) -> 0.020664764 | C10: fraction | D10: Adopted Harrison relief scaled by dose ratio (our event-average forcing / Harrison anchor forcing). Assumes relief ~linear in dose; only modest extrapolation.
A11: Coverage per tonne | B11: ='5a. Cooling Model - Local'!B11 -> 2910.9272 | C11: km2/tonne | D11: Tab 5a area-per-tonne derivation.
A12: Tonnes per heatwave | B12: =(B6/'5a. Cooling Model - Local'!B11)*(B7/'5a. Cooling Model - Local'!B24)/$B$3 -> 1037.4701 | C12: tonnes | D12: Area / coverage per tonne x 3-day cycles over the heatwave / delivery factor. First-principles event tonnage.
A13: Per-vessel output during event | B13: ='3a. Outputs - Dedicated Vessel'!$B$22*(B7/365) -> 163.72131 | C13: tonnes | D13: Annual per-vessel-unit production (3a, 33% utilization) x event fraction. Vessel-unit = tab-2 layout (~5,780 nozzles).
A14: Vessels required for the event | B14: =B12/B13 -> 6.3368056 | C14: vessels | D14: Event tonnage / per-vessel event output.
A15: Charter rate (bareboat: hull + crew) | B15: ='2. Cost Inputs'!B56/7 -> 21428.571 | C15: $/vessel/day | D15: Tab 2 B56 (weekly) / 7. Hull and crew only; mounted gear is row 22.
A16: Season charter cost | B16: =B14*B7*B15 -> 20504092 | C16: $ | D16: Vessels x days x rate.
A17: Temporary mounting & removal | B17: =B14*'3b. Outputs - Ship Piggyback'!B5*2 -> 1267361.1 | C17: $ | D17: Tab-3b containerized mounting per vessel, install + removal.
A18: Vessel fuel | B18: =B14*B7*('2. Cost Inputs'!B25+'2. Cost Inputs'!B26)*'2. Cost Inputs'!D25 -> 16103914 | D18: Vessels x days x fuel usage (propulsion + hotel) x price
A19: Seasonal operating (spray energy + technicians) | B19: =B12*'2. Cost Inputs'!B24*'2. Cost Inputs'!D24+B14*'3b. Outputs - Ship Piggyback'!B7*(B7/365) -> 9913216.7 | C19: $ | D19: Spray energy + one technician per vessel for the season. Charter includes crew and hull.
A20: Cost per heatwave (chartered, incl. row 22) | B20: =SUM(B16:B19)+B22 -> 52188203 | C20: $ | D20: Pay only for the season: bareboat charter + mounting + fuel + operating + the mounted spray train's capital share (row 22).
A21: Cost per hectare | B21: =B20/(B6*100) -> 17.396068 | C21: $/ha | D21: Linear in area; same $/ha at any scale.
A22: Mounted spray-train capital (event share) | B22: =B14*B7*'2. Cost Inputs'!B58 -> 4399619.2 | C22: $ | D22: Vessels x days x tab 2 B58 (nozzles, compressors, skid, amortized per vessel-day). Included in row 20.
A23: Reef ROI
A24: Bleaching-stress relief, 2015/16 event | B24: 0.5 | C24: fraction | D24: Harrison et al. 2019, modeled. | G24: Harrison et al. 2019 (T14), p.57: "an average reduction in bleaching stress of ~50 percent in 2015/2016".
A25: Bleaching-stress relief, 2016/17 event | B25: 0.65 | C25: fraction | D25: Harrison et al. 2019, modeled. | G25: Harrison et al. 2019 (T14), p.57: "~65 percent in 2016/2017"
A26: Adopted relief (Harrison) | B26: 0.57 | C26: fraction | D26: Average of the two events. | E26: Calculated: average of the two T14 events (0.5, 0.65).
A27: Reef total asset value | B27: =B31*'2. Cost Inputs'!B8 -> 66.5 | C27: $ billion (USD) | D27: Deloitte Access Economics 2025 'At What Cost?': A$95B GBR valuation at 0.7 USD/AUD.
A28: Value at risk in a severe bleaching event | B28: =B27*10^9*B32 -> 13300000000 | C28: $ | D28: Reef asset value x ~20% at risk in a severe bleaching event. A$95B already blends present + future value; no further discounting.
A29: Value protected | B29: =B28*B10 -> 2.7484135e+08 | C29: $ | D29: Value at risk x implied relief.
A30: ROI: value protected per dollar spent | B30: =B29/B20 -> 5.2663502 | C30: x | D30: Per heatwave event, on the chartered-fleet cost. Same-day accounting.
A31: GBR asset valuation (Deloitte Access Economics 2025) | B31: 95 | C31: A$ billion | D31: Deloitte 'At What Cost?' 2025. Converted at tab 2 B8. Until 10/07 typed inside B27.
A32: Share of reef value at risk in a severe bleaching event | B32: 0.2 | C32: fraction | D32: Assumption (~20%). Until 10/07 typed inside B28.
A33: Gut Check - Harrison et al. 2019 (Published Coupled Model)
A34: Harrison 2019 coupled-model gut check. Credits two effects we exclude: multi-day persistence and a mobile fleet chasing susceptible clouds.
A35: Event-average forcing achieved (Harrison) | B35: 22 | C35: W/m2 | D35: Coupled-model result: ~6.8% reef-wide dimming. RRAP conversion: 5 W/m2 ~ 1.5% reef-wide. | E35: Harrison et al. 2019 (T14), p.57: "reduction of around 6.7 percent of incoming shortwave solar radiation over the latitudinal extent of the Reef". File held.
A36: Deployment scope | B36: Reef-wide fleet | C36: - | D36: Mobile fleet; vessels brighten clouds wherever conditions suit.
A37: Dose ratio (ours / his) | B37: =B9/B35 -> 0.036253971 | C37: fraction | D37: This-deployment forcing / Harrison anchor forcing.
A38: Value protected if his assumptions held | B38: =B28*B26 -> 7.581e+09 | C38: $ | D38: Value at risk x Harrison adopted relief.
A39: ROI if his assumptions held | B39: =B38/B20 -> 145.26271 | C39: x | D39: Optimistic end of bracket; requires Harrison persistence + mobility assumptions, on the same chartered cost.
A40: =CONCATENATE("Bracket: ",TEXT(B30,"0.0"),"x under our same-day accounting to ",TEXT(B39,"0.0"),"x if Harrison persistence and mobility assumptions hold - both priced on the chartered fleet.") -> Bracket: 5.3x under our same-day accounting to 145.3x if Harrison persistence and mobility assumptions hold - both priced on the chartered fleet.

Sheet 5c-alt. Benefit - Reef (Zhao)
A1: Alternative reef scenario: Zhao 2026 preprint
A2: Input / step | B2: Value | C2: Source cell
A3: Delivery rate (particles/s per W/m2) | B3: =B9/B17 -> 3.2679739e+17
D5: Sources
A6: Station count | B6: 75 | C6: Zhao preprint | D6: Zhao et al. 2026 preprint (doi:10.5194/egusphere-2026-1251), p.6: "75 source points" (EXP20).
A7: Station spacing (km) | B7: 20 | C7: Zhao preprint | D7: Zhao et al. 2026, p.6: source points "distributed at a fine spatial spacing of 20 km".
A8: Emission per station (particles/s) | B8: 1e+16 | C8: Zhao preprint | D8: Zhao et al. 2026, p.6: "aerosol flux of the 1x10^16 particles per second... at each of 75 source points"
A9: Total emission (particles/s) | B9: =B6*B8 -> 7.5e+17
A10: Spray footprint (km2) | B10: =B6*B7^2 -> 30000
A12: Event season length (days), Harrison's window | B12: 151 | C12: T14 report text | D12: Harrison et al. 2019 (T14), p.39: summer window "from 1 December to 30 April" = 151 days.
A13: Zhao's albedo increase (absolute) | B13: =ROUND(0.51-0.48,3) -> 0.03 | C13: Zhao Fig. 8e: CTRL 0.48, EXP20 0.51; '+6.2%' is the relative label. 340 x 0.03 = 10.2 W/m2. | D13: Zhao et al. 2026, Fig. 8e: CTRL 0.48 vs EXP20 0.51 albedo.
A14: Cloud-top shortwave, 24-h average (W/m2) | B14: 340 | D14: Assumption (24-h mean cloud-top shortwave, GBR summer)
A15: Forcing where it works (W/m2) | B15: =B13*B14 -> 10.2
A16: Cloud availability | B16: 0.225 | C16: T14 D0.0676 | D16: Harrison et al. 2019 (T14), scenario D0.0676 basis
A17: Forcing target (W/m2) | B17: =B15*B16 -> 2.295
A19: Harrison SST response (°C per W/m2) | B19: ='5a. Cooling Model - Local'!B25 -> 0.0225 | C19: live: tab 5a (T14 Fig 15)
A20: Cooling (°C) | B20: =B17*B19 -> 0.0516375
A23: One nozzle's output (particles/s) | B23: ='1. Technology Description'!B8 -> 1730000000000 | C23: live: tab 1
A24: In-window fraction | B24: ='1. Technology Description'!B9 -> 0.71 | C24: live: tab 1
A25: Nozzle array per vessel | B25: =$B$8/(B23*B24) -> 8141.3336
A26: Equipment availability | B26: ='2. Cost Inputs'!B5 -> 0.9 | C26: live: tab 2
A27: Spray-time fraction | B27: 0.95 | D27: Assumption (spray uptime within events).
A28: Per-vessel continuous-equivalent (particles/s) | B28: =$B$8*B26*B27 -> 8.55e+15
A29: Season particle count | B29: =B17*B3*B12*86400 -> 9.7848e+24
A30: Per-vessel season particles | B30: =B28*B12*86400 -> 1.1154672e+23
A31: Vessels needed | B31: =B29/B30 -> 87.719298
A32: Fleet identity | B32: =IF(ABS(B31*B30/B29-1)<0.001,"MATCH","MISMATCH") -> MATCH
A34: Power per nozzle (W) | B34: ='1. Technology Description'!B17 -> 512 | C34: live: tab 1
A35: Spray power per vessel (kW) | B35: =B25*B34/1000 -> 4168.3628
A36: Charter rate ($/vessel/day) | B36: ='5c. Benefit - Local - Reef'!B15 -> 21428.571 | C36: live: tab 5c
A37: Weeks in the season | B37: =B12/7 -> 21.571429
A38: Temporary mounting & removal ($/vessel) | B38: ='3b. Outputs - Ship Piggyback'!B5*2 -> 200000 | C38: live: tab 3b (same as tab 5c)
A39: Season charter cost, fleet ($) | B39: =B31*B12*B36 -> 2.8383459e+08
A40: Mounting & removal, fleet ($) | B40: =B31*B38 -> 17543860
A41: Spray-hours per vessel per event | B41: =B12*24*B27*B26 -> 3098.52
A42: Electricity price ($/kWh) | B42: ='2. Cost Inputs'!D24 -> 0.3 | C42: live: tab 2
A43: Spray energy cost, fleet | B43: =B31*B35*B41*B42 -> 3.398883e+08
A44: Technician cost ($/vessel-year) | B44: ='3b. Outputs - Ship Piggyback'!B7 -> 180000 | C44: live: tab 3b
A45: Technician cost, fleet | B45: =B31*B44*((B12/7)/52) -> 6550028.9
A46: Total season cost of chartering and running the fleet (incl. row 47) | B46: =B39+B40+B43+B45+B47 -> 7.0871994e+08
A47: Mounted spray-train capital, fleet ($) | B47: =B31*B12*'2. Cost Inputs'!B58 -> 60903164 | C47: live: tab 2
A48: Harrison anchor forcing (W/m2) | B48: ='5c. Benefit - Local - Reef'!B35 -> 22 | C48: live: tab 5c
A49: Harrison relief at anchor | B49: ='5c. Benefit - Local - Reef'!B26 -> 0.57 | C49: live: tab 5c
A50: Value at risk ($) | B50: ='5c. Benefit - Local - Reef'!B28 -> 13300000000 | C50: live: tab 5c
A51: Relief (fraction of damage averted) | B51: =B17/B48*B49 -> 0.059461364
A52: Damage averted ($) | B52: =B51*B50 -> 7.9083614e+08
A54: Implied price of 10^16 particles ($) | B54: =B46/B29*10^16 -> 0.72430703
A55: ROI | B55: =B52/B46 -> 1.1158655

Sheet 5d. Benefit - Local - City
A1: Local Benefits: Heat-Death Reduction (City Cooling)
A2: Same cooling model as 5c; here a degree buys lives, not bleaching relief. Chartered seasonal fleet. Order-of-magnitude only.
A3: Local on-target delivery factor (applies to both profiles) | B3: 0.5 | C3: fraction | D3: Fraction of sprayed cooling that reaches the target city (rest drifts off). Same factor on tab 5c. | G3: Assumption (same factor as 5c).
A4: Our Calculation - Deployment and Cost (Chartered Fleet)
A5: Heat mortality +5.7% per 1C above threshold (RR 1.057, 326-city study). European heat plans bound the deliverable benefit (~25% reduction).
A6: Input | B6: Value | C6: Unit | D6: Source / basis | G6: Sources
A7: City area to cool | B7: 50000 | C7: hectares | D7: A large metro core (500 km2). | G7: Assumption (large metro core; 50,000 ha = 500 km2).
A8: Peak cooling delivered | B8: 0.8 | C8: degC | D8: Temperature shaved off the hottest part of extreme days. | G8: Assumption (peak cooling shaved on hottest days).
A9: Extreme-heat days per year | B9: 14 | C9: days | D9: Average heatwave days (~13.7/yr in 2010s globally). | G9: Literature-scale value: ~13.7 heatwave days/yr global average in 2010s ().
A10: Coverage per tonne | B10: ='5a. Cooling Model - Local'!B11 -> 2910.9272 | C10: km2/tonne | D10: Tab 5a area-per-tonne derivation.
A11: Tonnes per season | B11: =(B7/100/B10)*(B9/'5a. Cooling Model - Local'!B24)/$B$3 -> 1.6031547 | C11: tonnes | D11: Area / coverage per tonne x 3-day aerosol cycles over the heat days / delivery factor.
A12: Per-vessel output during season | B12: ='3a. Outputs - Dedicated Vessel'!$B$22*(B9/365) -> 15.17946 | C12: tonnes | D12: Annual per-vessel production (tab 2, at 33% utilization) x season fraction of year.
A13: Vessels required for the season | B13: =B11/B12 -> 0.10561343 | C13: vessels | D13: Season tonnage / per-vessel season output.
A14: Charter rate, bareboat workboat class | B14: ='2. Cost Inputs'!B56 -> 150000 | C14: $/vessel/week | D14: Pulled from tab 2 B56. Hull and crew only; mounted gear is row 20. | G14: Assumption: no market quote
A15: Season charter cost | B15: =B13*(B9/7)*B14 -> 31684.028 | C15: $ | D15: Vessels x weeks of extreme heat x rate.
A16: Temporary mounting & removal | B16: =B13*'3b. Outputs - Ship Piggyback'!B5*2 -> 21122.685 | C16: $ | D16: Tab-3b containerized mounting per vessel, install + removal.
A17: Seasonal operating (spray energy + technicians) | B17: =B11*'2. Cost Inputs'!B24*'2. Cost Inputs'!D24+B13*'3b. Outputs - Ship Piggyback'!B7*(B9/365) -> 15318.436 | C17: $ | D17: Spray energy + one technician per vessel for the season. Charter includes crew and hull.
A18: Cost per season (chartered, incl. row 20) | B18: =SUM(B15:B17)+B20 -> 74923.678 | C18: $ | D18: Pay only for the season: charter + mounting + seasonal operating. Same chartered-fleet frame as 5c.
A19: Cost per hectare | B19: =B18/B7 -> 1.4984736 | C19: $/ha | D19: Linear in area; same $/ha at any scale.
A20: Mounted spray-train capital (season share) | B20: =B13*B9*'2. Cost Inputs'!B58 -> 6798.5285 | C20: $ | D20: Vessels x heat days x tab 2 B58. Included in row 18. Until 10/07 the city fleet carried no spray-train capital at all.
A21: City ROI
A22: City population | B22: 2000000 | C22: people | D22: A mid-large city. | G22: Assumption (mid-large city).
A23: Baseline heat deaths / extreme season | B23: 200 | C23: deaths | D23: Excess deaths in the city during the dangerous season, pre-intervention. | G23: Assumption (baseline excess deaths per extreme season).
A24: Mortality rise per degC | B24: 0.057 | C24: per degC | D24: RR 1.057 per 1C above threshold (326-city study). | G24: 326-city study (as noted);
A25: Daily-mean realized cooling (RR basis) | B25: =B8*B30 -> 0.352 | C25: degC | D25: RR 1.057 is against daily-mean temperature, not peak. 0.44 converts peak shaving to the daily-mean dose the epidemiology sees.
A26: Deaths averted per season | B26: =B23*(1-1/(1+B24)^B25) -> 3.864774 | C26: deaths | D26: Baseline deaths x reduction at realized daily-mean cooling. Availability is already inside 5a's realization factor, so no separate availability halving.
A27: Value of a statistical life | B27: 10000000 | C27: $/life | D27: Assumption: US federal range. | G27: Assumption (US-federal-range VSL).
A28: Value protected | B28: =B26*B27 -> 38647740 | C28: $ | D28: Deaths averted x statistical-life value.
A29: ROI: value protected per dollar spent | B29: =B28/B18 -> 515.82813 | C29: x | D29: Per extreme-heat season, on the chartered-fleet cost.
A30: Peak to daily-mean conversion | B30: 0.44 | C30: fraction | D30: Share of a peak-hour cooling that shows up in the daily mean the mortality study uses. Assumption. Until 10/07 typed inside B25.
A31: Gut Check - Comparison Anchors
A32: No published targeted city cooling by MCB; first-of-kind profile. Two anchors bracket below: urban cooling economics; geoengineering epidemiology.
A33: Input | B33: Value | C33: Unit | D33: Source / basis
A34: Urban passive cooling, benefit-cost range | B34: 1.5 - 15.2 | C34: $ per $1 | D34: Estrada et al. 2017 (1,692 cities), via World Bank Cool Cities primer. Net benefit per $1 of passive cooling. | G34: Estrada et al. 2017, Nat. Clim. Change 7:403-406, p.2: Policy B BCR &quot;ranging from US$6.00 without GCC to US$15.24 under RCP8.5&quot;; Policy D &quot;between US$1.59 and US$3.96&quot;. Via World Bank Cool Cities primer. Primer link: https://openknowledge.worldbank.org/handle/10986/34218
A35: Solar geoengineering mortality benefit:risk | B35: 13 | C35: x | D35: Harding, Keith, Vecchi & Yang 2024 (PNAS): stratospheric sulfate, mortality benefits vs risks. Only other published cooling-for-lives number. | G35: Harding, Keith, Vecchi & Yang 2024 (PNAS),
A36: This profile, benefit-cost at $10M statistical life | B36: =B29 -> 515.82813 | C36: x | D36: Benefit-cost at $10M per statistical life, on the daily-mean realized dose and the chartered cost.
A37: =CONCATENATE("This profile (",TEXT(B29,"0.0"),"x on the daily-mean realized dose) sits at the top of the demonstrated urban-cooling range and near the global geoengineering mortality anchor. The dose basis is daily-mean, not instantaneous peak - the epidemiology does not support a peak-based dose.") -> This profile (515.8x on the daily-mean realized dose) sits at the top of the demonstrated urban-cooling range and near the global geoengineering mortality anchor. The dose basis is daily-mean, not instantaneous peak - the epidemiology does not support a peak-based dose.

Sheet 6a. Cooling Model - Global
A1: Global Cooling Model: Tonnage to Cooling via Earth-System Models
A2: Tonnes of sea salt per year into global cooling, via published regional simulations from three ESMs seeding real ocean regions. Includes cloud adjustments and feedbacks the bottom-up model omits.
A3: Basis conversion: CESM2/E3SMv2 emit 90 nm, UKESM1 172 nm (Hirasawa 2026, J. Climate). Restate tonnages at our 150 nm by (d_ours/d_model)^3 x (model CCN fraction / our CCN fraction), so we match cloud droplets, not raw particle counts; CCN fractions from Hirasawa 2026 preprint, Table 1). Then gross up for plume survival; ESMs emit diffuse fluxes, ours is a point source. Assumes (1) forcing is mostly cloud forcing, roughly true for CESM2, and (2) our 150 nm and the models' 90/172 nm particles stay airborne with an equally long lifetime.
A4: A. Published region-to-global conversion
A5: Hirasawa et al. 2026, J. Climate 39(2): 14 regions, 3 models, equal-forcing emissions. Midlatitude oceans beat the classic subtropical stratocumulus trio in all three models: stronger forcing per ton, better feedbacks, no remote warming patches.
A6: Strategy | B6: Model | C6: Emission (Tg/yr) | D6: Global cooling (K) | E6: Efficiency (K per Tg/yr) | G6: Notes
A7: Subtropical (3 regions) | B7: CESM2 | C7: 7.5 | D7: -1.042 | E7: -0.14 | G7: Optimistic end. CESM2 sits at the upper end of CMIP6 aerosol-cloud forcing.
A8: Subtropical (3 regions) | B8: E3SMv2 | C8: 49.5 | D8: -1.145 | E8: -0.0231 | G8: Middle of the envelope.
A9: Subtropical (3 regions) | B9: UKESM1.0 | C9: 150 | D9: -1.134 | E9: -0.00756 | G9: Pessimistic end. Emits 172nm particles, closest to our 150nm design point.
A10: Midlatitude (5 regions) | B10: CESM2 | C10: 12.5 | D10: -2.948 | E10: -0.236 | G10: Strongest efficiency in the study.
A11: Midlatitude (5 regions) | B11: E3SMv2 | C11: 82.5 | D11: -3.065 | E11: -0.0372
A12: Midlatitude (5 regions) | B12: UKESM1.0 | C12: 250 | D12: -1.886 | E12: -0.00754
A13: Midlatitude (5 regions) | B13: CESM2-Ghosh | C13: =C10 -> 12.5 | D13: =D10*(12.9/7.21) -> -5.2745076 | E13: =D13/C13 -> -0.42196061 | G13: Scaled from CESM2 by salt needed for -2 W/m2: CESM2 12.9 vs CESM2-Ghosh 7.21 Tg/yr (Hirasawa 2026 preprint, Table 2). Same model and particles, newer activation scheme (Ghosh et al. 2025). Cooling is scaled, not a simulated run.
A14: B. The 20-30x climate model spread
A15: Models disagree ~order-of-magnitude on tons for equal forcing (2.5 vs 50 Tg/yr per region). Part cloud susceptibility, part particle size: count per ton scales 1/d^3.
A16: CESM2 emitted size | B16: 90 | C16: nm | D16: 0.157 | E16: CCN fraction | G16: Model CCN fraction (Hirasawa 2026 preprint, Table 1)
A17: CESM2-Ghosh emitted size | B17: 90 | C17: nm | D17: 0.157 | E17: CCN fraction | G17: Model CCN fraction (Hirasawa 2026 preprint, Table 1)
A18: E3SMv2 emitted size | B18: 90 | C18: nm | D18: 0.131 | E18: CCN fraction | G18: Model CCN fraction (Hirasawa 2026 preprint, Table 1)
A19: UKESM1.0 emitted size | B19: 172 | C19: nm | D19: 0.805 | E19: CCN fraction | G19: Model CCN fraction (Hirasawa 2026 preprint, Table 1)
A20: Our design point | B20: ='1. Technology Description'!B10 -> 150 | C20: nm | D20: ='1. Technology Description'!B9 -> 0.71
A22: C. Bottom up gut check
A23: Our bottom-up chain implies a global forcing per Tg/yr. Compare with each model's per-region efficiency (about -0.6 W/m2 per region at nominal):
A24: Our forcing per Tg/yr (delivery- and activation-adjusted) | B24: =('5a. Cooling Model - Local'!B19*'5a. Cooling Model - Local'!B11*10^6/(5.1*10^14)*('5a. Cooling Model - Local'!B24/365)*10^6)*'5a. Cooling Model - Local'!B22 -> 0.037416901 | C24: ESM restated at our basis | G24: Local forcing x area / Earth area x lifetime. Now includes the realization factor, so apples-to-apples with the published all-weather efficiencies.
A25: CESM2 implied forcing efficiency | B25: 0.24 | C25: =B25*($B$16/$B$20)^3*$D$20/D16 -> 0.23443567 | D25: x (d_model/d_ours)^3 x (our CCN fraction / model CCN fraction): a tonne of 90 nm holds (150/90)^3 = 4.6x more particles than 150 nm, but only 15.7% of CESM2's become droplets vs our 71%, so per tonne the two make about the same number of droplets
A26: E3SMv2 implied forcing efficiency | B26: 0.0364 | C26: =B26*($B$18/$B$20)^3*$D$20/D18 -> 0.042613008
A27: UKESM1.0 implied forcing efficiency | B27: 0.012 | C27: =B27*($B$19/$B$20)^3*$D$20/D19 -> 0.015957148
A29: D. Aerosol required for 1 K of global cooling | H29: Sources
A30: Targeted spraying bonus | B30: 1 | C30: fraction | D30: 100% is neutral. The study assume even spraying over the region. There is likely some benefit of targeted spraying. | H30: Structural default (neutral; no targeting bonus).
A31: Target global cooling | B31: 1 | C31: K | H31: Structural default (target cooling 1 K).
A32: Plume survival to cloud base (scenario) | B32: 0.3 | C32: fraction | D32: Catch-all for every loss, including particles too small to become droplets. Assumption: same basis as the tab 5a survival factor (Frontiers plume review 2025; open research gap).
A33: Model | B33: Efficiency (K per Tg/yr) | C33: Tg/yr (model size basis) | D33: Tons/yr (model basis) | E33: Emitted size (nm) | F33: Size factor (150/d)^3 x CCN ratio | G33: Tg/yr at our basis | H33: Tg/yr / survival | I33: Tons/yr (our basis)
A34: CESM2 | B34: 0.236 | C34: =$B$31/B34/$B$30 -> 4.2372881 | D34: =C34*10^6 -> 4237288.1 | E34: =$B$16 -> 90 | F34: =($B$20/E34)^3*D16/$D$20 -> 1.023735 | G34: =C34*F34 -> 4.3378602 | H34: =G34/$B$32 -> 14.459534 | I34: =H34*10^6 -> 14459534
A35: CESM2-Ghosh | B35: =-E13 -> 0.42196061 | C35: =$B$31/B35/$B$30 -> 2.3698895 | D35: =C35*10^6 -> 2369889.5 | E35: =$B$17 -> 90 | F35: =($B$20/E35)^3*D17/$D$20 -> 1.023735 | G35: =C35*F35 -> 2.4261388 | H35: =G35/$B$32 -> 8.0871293 | I35: =H35*10^6 -> 8087129.3
A36: E3SMv2 | B36: 0.0372 | C36: =$B$31/B36/$B$30 -> 26.88172 | D36: =C36*10^6 -> 26881720 | E36: =$B$18 -> 90 | F36: =($B$20/E36)^3*D18/$D$20 -> 0.85419927 | G36: =C36*F36 -> 22.962346 | H36: =G36/$B$32 -> 76.541153 | I36: =H36*10^6 -> 76541153
A37: UKESM1.0 | B37: 0.00754 | C37: =$B$31/B37/$B$30 -> 132.62599 | D37: =C37*10^6 -> 1.3262599e+08 | E37: =$B$19 -> 172 | F37: =($B$20/E37)^3*D19/$D$20 -> 0.75201407 | G37: =C37*F37 -> 99.736614 | H37: =G37/$B$32 -> 332.45538 | I37: =H37*10^6 -> 3.3245538e+08
A39: Note: Not accounting for direct aerosol forcing scales with salt mass, not droplets; significant above ~50 Tg/yr, dominant above ~200 Tg/yr.
A41: D. What a degree-year of cooling is worth (inputs; tabs 6b and 6c read these)
A42: Global GDP | B42: 110 | C42: $ trillion | G42: World GDP ~$110T (2025).
A43: Damage: low (older IAM / Nordhaus-style) | B43: 0.6 | C43: % GDP per degC | G43: DICE-2016R (Nordhaus 2017, w22933): 0.227% GDP per degC^2 ≈ 3.6% at 4C
A44: Damage: central (statistical class; Burke et al. 2015 anchor) | B44: 3.3 | C44: % GDP per degC | G44: Burke, Hsiang & Miguel 2015 (Nature 527:235): ~23% GDP/capita at ~3.7C (~6%/degC). 3.3%/degC is conservative within the statistical class (Kahn 2021 ~2.5%; Bilal & Kanzig 2024 12% peak). Replaces Kotz 2024, retracted Dec 2025.
A45: Damage: high (Bilal-Kanzig 2024) | B45: 12 | C45: % GDP per degC | G45: Bilal & Kanzig 2024 (w32450): 12% GDP per degC

Sheet 6b. Benefit - Global - Vessel
A1: Global Cooling via Dedicated Vessel: Cost and Benefit-Cost
A2: One cost basis here: the dedicated spray vessel, levelized on 3a. Tonnage from 6a; the cheaper piggyback case is 6c.
A4: A. Cost to cool the planet (dedicated vessel)
A5: Target global cooling | B5: ='6a. Cooling Model - Global'!B31 -> 1 | C5: K
A6: Cost per tonne (dedicated vessel, tab 3a base) | B6: ='3a. Outputs - Dedicated Vessel'!G5 -> 54047.979 | C6: $/tonne
A7: Tonnage per model from 6a (midlatitude), restated at 150 nm and grossed up for survival; cost at 3a dedicated-vessel levelized.
A9: Model | B9: Efficiency (K per Tg/yr) | C9: Tg/yr (150 nm basis) | D9: Tons/yr (150 nm, post-survival) | E9: $/yr
A10: CESM2 | B10: ='6a. Cooling Model - Global'!B34 -> 0.236 | C10: ='6a. Cooling Model - Global'!G34 -> 4.3378602 | D10: ='6a. Cooling Model - Global'!I34 -> 14459534 | E10: =D10*$B$6 -> 7.8150858e+11
A11: CESM2-Ghosh | B11: ='6a. Cooling Model - Global'!B35 -> 0.42196061 | C11: ='6a. Cooling Model - Global'!G35 -> 2.4261388 | D11: ='6a. Cooling Model - Global'!I35 -> 8087129.3 | E11: =D11*$B$6 -> 4.3709299e+11
A12: E3SMv2 | B12: ='6a. Cooling Model - Global'!B36 -> 0.0372 | C12: ='6a. Cooling Model - Global'!G36 -> 22.962346 | D12: ='6a. Cooling Model - Global'!I36 -> 76541153 | E12: =D12*$B$6 -> 4.1368946e+12
A13: UKESM1.0 | B13: ='6a. Cooling Model - Global'!B37 -> 0.00754 | C13: ='6a. Cooling Model - Global'!G37 -> 99.736614 | D13: ='6a. Cooling Model - Global'!I37 -> 3.3245538e+08 | E13: =D13*$B$6 -> 1.7968541e+13
A14: B. What a degree-year of cooling is worth
A15: Damage-function lookup: do not reinvent, look up damage per degree and multiply. Low/central/high band: the three anchors are different kinds of quantity, so read the band as scenario spread, not a confidence interval. Break-even depends on the cost scenario.
A16: Global GDP | B16: ='6a. Cooling Model - Global'!$B$42 -> 110 | C16: $ trillion | E16: Pulled from tab 6a (B42).
A17: Target global cooling (from A above) | B17: =B5 -> 1 | C17: K
A19: Damage estimate | B19: % GDP per degC | C19: $B/degC-yr | D19: Value of target cooling ($B/yr) | E19: Source
A20: Low (older IAM / Nordhaus-style) | B20: ='6a. Cooling Model - Global'!$B$43 -> 0.6 | C20: =B16*1000*B20/100 -> 660 | D20: =C20*B17 -> 660 | E20: Pulled from tab 6a (B43); source there.
A21: Central (statistical class; Burke et al. 2015 anchor) | B21: ='6a. Cooling Model - Global'!$B$44 -> 3.3 | C21: =B16*1000*B21/100 -> 3630 | D21: =C21*B17 -> 3630 | E21: Pulled from tab 6a (B44); source there.
A22: High (Bilal-Kanzig 2024) | B22: ='6a. Cooling Model - Global'!$B$45 -> 12 | C22: =B16*1000*B22/100 -> 13200 | D22: =C22*B17 -> 13200 | E22: Pulled from tab 6a (B45); source there.
A23: All values $B/yr: global GDP ($110T) x damage %/degC. One degree-year ≈ $700B low, $3,600B central, $13,000B high. Central = Burke 2015 at 3.3%/degC (post-Kotz retraction).
A25: C. Benefit-cost ratio
A26: Value of the cooling (section B, central damage estimate) divided by its cost (section A).
A28: Cost case (model) | B28: Cost ($B/yr) | C28: Value ($B/yr, central damage) | D28: Benefit-cost ratio
A29: CESM2 (optimistic) | B29: =E10 -> 7.8150858e+11 | C29: =$D$21*10^9 -> 3630000000000 | D29: =C29/B29 -> 4.6448626
A30: CESM2-Ghosh (most optimistic) | B30: =E11 -> 4.3709299e+11 | C30: =$D$21*10^9 -> 3630000000000 | D30: =C30/B30 -> 8.3048689
A31: E3SMv2 (central) | B31: =E12 -> 4.1368946e+12 | C31: =$D$21*10^9 -> 3630000000000 | D31: =C31/B31 -> 0.87746978
A32: UKESM1 (pessimistic, our size) | B32: =E13 -> 1.7968541e+13 | C32: =$D$21*10^9 -> 3630000000000 | D32: =C32/B32 -> 0.20201974
A33: Benefit-cost at the dedicated-vessel cost from tab 3a. Piggyback scenario and fleet numbers on 6c.

Sheet 6c. Benefit - Global Piggyback
A1: Global Cooling via Container-Ship Piggyback: Cost and Benefit-Cost
A2: One cost basis here: the container-ship piggyback from tab 3b, read directly the way 6b reads 3a. Tonnage from 6a. Every input traces to tabs 1, 2 and 3b.
A4: A. Cost to cool the planet (container-ship piggyback)
A5: Target global cooling | B5: ='6a. Cooling Model - Global'!B31 -> 1 | C5: K
A6: Cost per tonne (container-ship piggyback, tab 3b) | B6: ='3b. Outputs - Ship Piggyback'!C32 -> 21674.005 | C6: $/tonne | D6: Reads tab 3b directly. Until 10/07 this section costed its own optimistic case (0.1x power, best-case prices, 43% utilization).
A17: Model | B17: Efficiency (K per Tg/yr) | C17: Tg/yr (150 nm basis) | D17: Tons/yr (150 nm, post-survival) | E17: $/yr
A18: CESM2 | B18: ='6a. Cooling Model - Global'!B34 -> 0.236 | C18: ='6a. Cooling Model - Global'!G34 -> 4.3378602 | D18: ='6a. Cooling Model - Global'!I34 -> 14459534 | E18: =D18*$B$6 -> 3.1339601e+11
A19: CESM2-Ghosh | B19: ='6a. Cooling Model - Global'!B35 -> 0.42196061 | C19: ='6a. Cooling Model - Global'!G35 -> 2.4261388 | D19: ='6a. Cooling Model - Global'!I35 -> 8087129.3 | E19: =D19*$B$6 -> 1.7528048e+11
A20: E3SMv2 | B20: ='6a. Cooling Model - Global'!B36 -> 0.0372 | C20: ='6a. Cooling Model - Global'!G36 -> 22.962346 | D20: ='6a. Cooling Model - Global'!I36 -> 76541153 | E20: =D20*$B$6 -> 1.6589533e+12
A21: UKESM1.0 | B21: ='6a. Cooling Model - Global'!B37 -> 0.00754 | C21: ='6a. Cooling Model - Global'!G37 -> 99.736614 | D21: ='6a. Cooling Model - Global'!I37 -> 3.3245538e+08 | E21: =D21*$B$6 -> 7.2056396e+12
A23: B. What a degree-year of cooling is worth
A24: Damage-function lookup: do not reinvent, look up damage per degree and multiply. Low/central/high band: the three anchors are different kinds of quantity, so read the band as scenario spread, not a confidence interval. Break-even depends on the cost scenario.
A25: Global GDP | B25: ='6a. Cooling Model - Global'!$B$42 -> 110 | C25: $ trillion | E25: Pulled from tab 6a (B42).
A26: Target global cooling (from A above) | B26: =B5 -> 1 | C26: K
A28: Damage estimate | B28: % GDP per degC | C28: $B/degC-yr | D28: Value of target cooling ($B/yr) | E28: Source
A29: Low (older IAM / Nordhaus-style) | B29: ='6a. Cooling Model - Global'!$B$43 -> 0.6 | C29: =B25*1000*B29/100 -> 660 | D29: =C29*B26 -> 660 | E29: Pulled from tab 6a (B43); source there.
A30: Central (statistical class; Burke et al. 2015 anchor) | B30: ='6a. Cooling Model - Global'!$B$44 -> 3.3 | C30: =B25*1000*B30/100 -> 3630 | D30: =C30*B26 -> 3630 | E30: Pulled from tab 6a (B44); source there.
A31: High (Bilal-Kanzig 2024) | B31: ='6a. Cooling Model - Global'!$B$45 -> 12 | C31: =B25*1000*B31/100 -> 13200 | D31: =C31*B26 -> 13200 | E31: Pulled from tab 6a (B45); source there.
A32: All values $B/yr: global GDP ($110T) x damage %/degC. One degree-year ≈ $700B low, $3,600B central, $13,000B high. Central = Burke 2015 at 3.3%/degC (post-Kotz retraction).
A34: C. Benefit-cost ratio
A35: Value of the cooling (section B, central damage estimate) divided by its cost (section A).
A37: Cost case (model) | B37: Cost ($B/yr) | C37: Value ($B/yr, central damage) | D37: Benefit-cost ratio
A38: CESM2 (optimistic) | B38: =E18 -> 3.1339601e+11 | C38: =$D$30*10^9 -> 3630000000000 | D38: =C38/B38 -> 11.582789
A39: CESM2-Ghosh (most optimistic) | B39: =E19 -> 1.7528048e+11 | C39: =$D$30*10^9 -> 3630000000000 | D39: =C39/B39 -> 20.709665
A40: E3SMv2 (central) | B40: =E20 -> 1.6589533e+12 | C40: =$D$30*10^9 -> 3630000000000 | D40: =C40/B40 -> 2.1881266
A41: UKESM1 (pessimistic, our size) | B41: =E21 -> 7.2056396e+12 | C41: =$D$30*10^9 -> 3630000000000 | D41: =C41/B41 -> 0.50377207
A42: ="Benefit-cost at the piggyback cost from tab 3b ("&TEXT($B$6,"$#,##0")&"/t). Dedicated-vessel case is 6b; fleet numbers in section D." -> Benefit-cost at the piggyback cost from tab 3b ($21,674/t). Dedicated-vessel case is 6b; fleet numbers in section D.
A44: D. Fleet scale and power sensitivity
A45: Piggyback-only question: how many ships, and what is the nozzle power draw worth?
A47: Per-ship aerosol output (tab 3b host-ship train) | B47: ='3b. Outputs - Ship Piggyback'!B43 -> 427.2363 | C47: t/yr | D47: Pulled from tab 3b (B43): the train sized to the ship's own 4.5 MW. Until 10/07 this assumed 2 MW from the host while 3b priced a 4.2 MW train.
A48: Annual fuel for own generation (t) | B48: ='3b. Outputs - Ship Piggyback'!B41*24*'3b. Outputs - Ship Piggyback'!B16*B50/1000 -> 2592 | C48: t/yr
A49: Own gensets burn ~200 g fuel/kWh (B50); the fuel is already priced inside the tab-2 energy rate. This row is for bunkering logistics only.
A50: Generator fuel rate | B50: 0.2 | C50: kg per kWh | D50: Until 10/07 typed inside B48.
A51: Fleet reference
A52: Fully cellular container ships (Alphaliner, Apr 2026) | B52: 6706 | C52: ships
A53: Sources: Alphaliner Apr 2026 (6,706 container ships); MDS Transmodal Apr 2025 via UNCTAD RMT 2025 (6,033); Alphaliner Monthly Monitor Jul 2024 size table (954 of 6,206 ships under 1,000 TEU).
A54: Eligible host ships (1,000 TEU and up) | B54: =ROUND(B52*D54,0) -> 5700 | C54: ships | D54: 0.85 | E54: D54 = share of the fleet of 1,000 TEU and up, 85% by count (Alphaliner Jul 2024). A 4.5 MW own-generation train needs ~30 TEU of slots, so feeders qualify; only the smallest class is excluded.
A55: Climate model | B55: Aerosol for 1K (t/yr) | C55: Vessels needed | D55: % of eligible fleet | E55: ="Cost at tab-1 power, "&TEXT($B$6,"$#,##0")&"/t ($B/yr)" -> Cost at tab-1 power, $21,674/t ($B/yr)
A56: CESM2 (optimistic) | B56: ='6a. Cooling Model - Global'!I34 -> 14459534 | C56: =B56/$B$47 -> 33844.348 | D56: =C56/$B$54 -> 5.9376049 | E56: =B56*$B$6/10^9 -> 313.39601
A57: CESM2-Ghosh | B57: ='6a. Cooling Model - Global'!I35 -> 8087129.3 | C57: =B57/$B$47 -> 18928.938 | D57: =C57/$B$54 -> 3.3208663 | E57: =B57*$B$6/10^9 -> 175.28048
A58: E3SMv2 (central) | B58: ='6a. Cooling Model - Global'!I36 -> 76541153 | C58: =B58/$B$47 -> 179154.14 | D58: =C58/$B$54 -> 31.430552 | E58: =B58*$B$6/10^9 -> 1658.9533
A59: UKESM1.0 (pessimistic) | B59: ='6a. Cooling Model - Global'!I37 -> 3.3245538e+08 | C59: =B59/$B$47 -> 778153.41 | D59: =C59/$B$54 -> 136.51814 | E59: =B59*$B$6/10^9 -> 7205.6396
A61: Nozzle power sensitivity
A62: To see this tab at a different nozzle power, change the selector on tab 1 (H17). Tab 3b re-sizes the train to the same 4.5 MW and every row above follows. Until 10/07 an energy-only approximation lived here.

Sheet References
A1: References: academic publications cited in this workbook
A2: Ref as cited | B2: Full citation | C2: Where used | D2: DOI / link
A3: Harrison et al. 2025 | B3: Harrison, L. P., Medcraft, C., & Harrison, D. P. (2025). Effervescent nozzle design to enable outdoor marine cloud brightening experimentation. Environmental Science: Atmospheres, 5(10), 1071-1080. | C3: Tabs 1 (particle output, CCN window, particle size, power, energy per tonne), 2 | D3: https://doi.org/10.1039/d5ea00073d
A4: Harrison et al. 2019 / T14 | B4: Harrison, D. P., Baird, M., Harrison, L., Utembe, S., Schofield, R., Escobar Correa, R., Mongin, M., & Rizwi, F. (2019). Environmental Modelling of Large Scale Solar Radiation Management. RRAP T14 Final Report (83 pp). | C4: 5a (local temperature sensitivity), 5c-alt (T14 scenarios, Fig 15) | D4: https://gbrrestoration.org/wp-content/uploads/2020/09/T14-Environmental-Modelling-of-Large-Scale-SRM_v3.03-3.pdf
A5: Zhao et al. 2026 (preprint) | B5: Zhao, W., Huang, Y., Siems, S., & Harrison, D. (2026). Sensitivity of Marine Cloud Brightening over the Great Barrier Reef to Spatial Variability in Aerosol Forcing: A Case Study using convection-permitting model. EGUsphere preprint, discussion started 23 March 2026. | C5: 5c-alt (main cooling basis), 5c | D5: https://doi.org/10.5194/egusphere-2026-1251
A6: Hernandez-Jaramillo et al. 2025 (ERL) | B6: Hernandez-Jaramillo, D. C., Harrison, L., Gunner, G., McGrath, A., Junkermann, W., Lieff, W., Hacker, J., Rosenfeld, D., Kelaher, B., & Harrison, D. P. (2025). First generation outdoor marine cloud brightening trial increases aerosol concentration at cloud base height. Environmental Research Letters, 20(5), 054065. | C6: Tab 1 (particle size, particles per tonne, energy notes), 6a (plume to cloud base) | D6: https://doi.org/10.1088/1748-9326/adccd7
A7: Hernandez-Jaramillo et al. 2025a (plume review) | B7: Hernandez-Jaramillo, D., Kelaher, B., & Harrison, D. (2025). A review of plume dispersion and measurement techniques applicable to marine cloud brightening. Frontiers in Marine Science, 12, 1450175. | C7: 5a (survival factor, activation diameter), 6a (plume survival) | D7: https://doi.org/10.3389/fmars.2025.1450175
A8: CS-01 2025 (RRAP report) | B8: Harrison, D., Ristovski, Z., Ryan, R., Zhao, W., Sulo, J., Horchler, J., Huang, Y., Schofield, R., Deschaseaux, E., Harrison, L., Holloway, C., Braga, R., Rosenfeld, D., & Siems, S. (2025). Reef Restoration and Adaptation Program - GBR Atmospheric Survey (CS-01) Final Report 2025 (33 pp). | C8: 5a (cloud availability 0.2; p.11) | D8: https://gbrrestoration.org/wp-content/uploads/2026/06/RRAP-CS-01_FINAL-REPORT-2025.pdf
A9: CS-06 2025 (RRAP report) | B9: Harrison, D. P., Ristovski, Z., Rosenfeld, D., Holloway, C., Cleary, M., Kourmatzis, A., Harrison, L., Braga, R. C., Medcraft, C., Hernandez-Jaramillo, D. C., et al. (2025). Reef Restoration and Adaptation Program - Cloud and Sky Brightening Development (CS-06) Final Report 2025 (56 pp). | C9: Tab 1 (particle size, power), 5a (survival, mixing depth, background droplets p.34, droplet enhancement), 3a | D9: https://gbrrestoration.org/wp-content/uploads/2026/06/RRAP-CS-06_FINAL-REPORT-2025.pdf
A10: Latham et al. 2012 | B10: Latham, J., Bower, K., Choularton, T., Coe, H., Connolly, P., Cooper, G., Craft, T., Foster, J., Gadian, A., et al. (2012). Marine cloud brightening. Philosophical Transactions of the Royal Society A, 370, 4217-4262. | C10: Tab 2 (required flux), foundational MCB concept | D10: https://doi.org/10.1098/rsta.2012.0086
A11: Hirasawa et al. 2026 | B11: Hirasawa, H., Henry, M., Mason, E., Rasch, P. J., Doherty, S. J., & Wood, R. (2026). Forcing Susceptibility and Climate Sensitivity to Midlatitude Marine Cloud Brightening. Journal of Climate, 39(2), 769-784. | C11: 6a (section A regional efficiencies, model emission sizes) | D11: https://doi.org/10.1175/JCLI-D-25-0337.1
A12: Estrada et al. 2017 | B12: Estrada, F., Botzen, W. J. W., & Tol, R. S. J. (2017). A global economic assessment of city policies to reduce climate change impacts. Nature Climate Change, 7, 403-406. | C12: 5d (urban passive cooling benefit-cost) | D12: https://doi.org/10.1038/nclimate3301
A13: Burke et al. 2015 | B13: Burke, M., Hsiang, S. M., & Miguel, E. (2015). Global non-linear effect of temperature on economic production. Nature, 527, 235-239. | C13: 6b, 6c (value of a degree of cooling, central damage estimate) | D13: https://doi.org/10.1038/nature15725
A14: Hirasawa et al. 2026 (preprint) | B14: Hirasawa, H., von Salzen, K., Henry, M., Smith, J., Bender, F. A.-M., Wang, C., Doherty, S., Wood, R., Rasch, P. J., and Haywood, J. (2026). On the Range of Marine Cloud Brightening Radiative Forcing across Earth System Models. EGUsphere preprint. | C14: 6a (model CCN fractions; CESM2-Ghosh scaling) | D14: https://doi.org/10.5194/egusphere-2026-5460
A15: Supporting files (not directly cited)
A16: ARIA proposal 2025 | B16: Harrison, D. P. et al. (2025). Marine Cloud Brightening in a complex world - moving beyond the Twomey effect. Proposal to the Advanced Research + Invention Agency: Exploring Climate Cooling Programme. Southern Cross University. | C16: Corroborates tab-1 nozzle specs (640 nozzles, ~10^15/s) | D16: https://doi.org/10.25918/misc.469
A17: PhD thesis 2024 | B17: Hernandez Jaramillo, D. C. (2024). Characterisation and dispersion of particle emissions for marine cloud brightening over the Great Barrier Reef. PhD thesis, Southern Cross University. | C17: Background on sprayer generations and plume measurements | D17: https://doi.org/10.25918/thesis.426
A18: Non-academic sources (websites, not downloaded)
A19: Nozzle price listing | B19: Alibaba product listing for effervescent nozzle hardware. | C19: Tab 2 (nozzle price) | D19: https://www.alibaba.com/product-detail/Two-fluid-Nozzle-Fuel-Burner-Gas_1601145712214.html
A20: Vessel charter / ship sizing | B20: Charter-market and vessel-spec websites used for ship sizing and charter rates. | C20: Tab 2, 3a-3d | D20: https://horizonoffshoreservices.com/wp-content/uploads/2024/07/HOS269.pdf ; https://www.rivieramm.com/news-content-hub/sticker-shock-price-of-psv-newbuildings-up-68-since-2016-79964
A21: World Bank Cool Cities primer | B21: World Bank (2020). Cool Cities: Reducing Urban Heat. Primer / report. | C21: 5d (urban passive cooling benefit-cost) | D21: https://openknowledge.worldbank.org/handle/10986/34218
